[
  {
    "id": "ml98p3gl",
    "questionNumber": 53,
    "questionText": "<p>Let a circle of radius 4 pass through the origin O , the points $\\mathrm{A}(-\\sqrt{3} a, 0)$ and $\\mathrm{B}(0,-\\sqrt{2} b)$, where $a$ and $b$ are real parameters and $a b \\neq 0$. Then the locus of the centroid of $\\triangle \\mathrm{OAB}$ is a circle of radius</p>\n",
    "options": [
      "<p>$\\frac{7}{3}$</p>\n",
      "<p>$\\frac{11}{3}$</p>\n",
      "<p>$\\frac{5}{3}$</p>\n",
      "<p>$\\frac{8}{3}$</p>"
    ],
    "correctOption": 3,
    "correctAnswer": null,
    "questionType": "MCQ",
    "marks": 4,
    "negativeMarks": -1,
    "subject": "Mathematics",
    "topic": "family-of-circle",
    "difficulty": "medium",
    "solution": "<p>Given a circle passes through $O(0,0), A(-\\sqrt{3} a, 0)$, and $B(0,-\\sqrt{2} b)$. Since $A$ lies on the x -axis and $B$ lies on the y -axis, $\\angle A O B=90^{\\circ}$. Thus $A B$ is the diameter of the circle.</p>\n<p>Diameter $d=2 \\times$ radius $=2(4)=8$.</p>\n<p>Using distance formula for $A B$ :</p>\n<p>$$ \\begin{gathered} \\sqrt{(-\\sqrt{3} a-0)^2+(0-(-\\sqrt{2} b))^2}=8 \\\\ 3 a^2+2 b^2=64 \\quad------(1) \\end{gathered} $$</p>\n<p>Let the centroid of $\\triangle O A B$ be $G(h, k)$.</p>\n<p>$$ \\begin{gathered} h=\\frac{0-\\sqrt{3} a+0}{3} \\Longrightarrow a=\\frac{-3 h}{\\sqrt{3}}=-\\sqrt{3} h \\\\ k=\\frac{0+0-\\sqrt{2} b}{3} \\Longrightarrow b=\\frac{-3 k}{\\sqrt{2}} \\end{gathered} $$</p>\n<p>Substitute $a$ and $b$ into (Eq. 1):</p>\n<p>$$ \\begin{gathered} 3(-\\sqrt{3} h)^2+2\\left(\\frac{-3 k}{\\sqrt{2}}\\right)^2=64 \\\\ 3\\left(3 h^2\\right)+2\\left(\\frac{9 k^2}{2}\\right)=64 \\\\ 9 h^2+9 k^2=64 \\\\ h^2+k^2=\\frac{64}{9} \\end{gathered} $$</p>\n<p>The locus is a circle $x^2+y^2=\\left(\\frac{8}{3}\\right)^2$.</p>\n<p>Radius $=\\frac{8}{3} $</p>",
    "section": "A",
    "type": "SCQ"
  },
  {
    "id": "m9dunos7",
    "questionNumber": 72,
    "questionText": "<p>The absolute difference between the squares of the radii of the two circles passing through the point $(-9,4)$ and touching the lines $x+y=3$ and $x-y=3$, is equal to ________ .</p>",
    "options": [],
    "correctOption": 0,
    "correctAnswer": null,
    "questionType": "MCQ",
    "marks": 4,
    "negativeMarks": -1,
    "subject": "Mathematics",
    "topic": "family-of-circle",
    "difficulty": "medium",
    "solution": "<p>$\\because x+y=3$ and $x-y=3$ are tangents</p>\n<p>$\\therefore \\quad$ Both circle centre will lie on $x$-axis</p>\n<p>$\\therefore(x-a)^2+y^2=r^2$</p>\n<p>Hence centre is $C(\\alpha, 0)$</p>\n<p>$$\\begin{aligned}\n&amp;r=\\sqrt{(\\alpha+9)^2+16}\\quad\\text{.... (1)}\\\\\n&amp;\\text { Also }\\left|\\frac{\\alpha-3}{\\sqrt{2}}\\right|=r \\quad\\text{.... (2)}\\\\\n&amp;\\begin{aligned}\n&amp; \\sqrt{(\\alpha+9)^2+16}=\\left|\\frac{\\alpha-3}{\\sqrt{2}}\\right| \\\\\n&amp; \\Rightarrow \\quad \\alpha=-5 \\text { or }-37 \\\\\n&amp; \\mathrm{r}=\\left|\\frac{-5-3}{\\sqrt{2}}\\right| \\text { or }\\left|\\frac{-37-3}{\\sqrt{2}}\\right| \\\\\n&amp; =4 \\sqrt{2} \\text { or } 20 \\sqrt{2} \\\\\n&amp; \\left|\\mathrm{r}_1^2-\\mathrm{r}_2^2\\right|=|32-800|=768\n\\end{aligned}\n\\end{aligned}$$</p>",
    "section": "B",
    "type": "SUBJECTIVE"
  },
  {
    "id": "1ldpsfpye",
    "questionNumber": 63,
    "questionText": "<p>Let a circle $$C_{1}$$ be obtained on rolling the circle $$x^{2}+y^{2}-4 x-6 y+11=0$$ upwards 4 units on the tangent $$\\mathrm{T}$$ to it at the point $$(3,2)$$. Let $$C_{2}$$ be the image of $$C_{1}$$ in $$\\mathrm{T}$$. Let $$A$$ and $$B$$ be the centers of circles $$C_{1}$$ and $$C_{2}$$ respectively, and $$M$$ and $$N$$ be respectively the feet of perpendiculars drawn from $$A$$ and $$B$$ on the $$x$$-axis. Then the area of the trapezium AMNB is :</p>",
    "options": [
      "$$2\\left( {2 + \\sqrt 2 } \\right)$$",
      "$$4\\left( {1 + \\sqrt 2 } \\right)$$",
      "$$3 + 2\\sqrt 2 $$",
      "$$2\\left( {1 + \\sqrt 2 } \\right)$$"
    ],
    "correctOption": 1,
    "correctAnswer": null,
    "questionType": "MCQ",
    "marks": 4,
    "negativeMarks": -1,
    "subject": "Mathematics",
    "topic": "family-of-circle",
    "difficulty": "medium",
    "solution": "Given circle is $x^{2}+y^{2}-4 x-6 y+11=0$, centre $(2,3)$\n\n<br/><br/>Tangent at $(3,2)$ is $x-y=1$\n\n<br/><br/>After rolling up by 4 units centre of $C_{1}$ is\n\n<br/><br/>$A \\equiv\\left(2+\\frac{4}{\\sqrt{2}}, 3+\\frac{4}{\\sqrt{2}}\\right)$\n\n<br/><br/>$\\Rightarrow A=(2+2 \\sqrt{2}, 3+2 \\sqrt{2})$\n\n<br/><br/>$B$ is the image of $A$ in $x-y=1$\n\n<br/><br/>$\\frac{x-(2+2 \\sqrt{2})}{1}=\\frac{y-(3+2 \\sqrt{2})}{-1}=\\frac{-2(-2)}{2}=2$\n\n<br/><br/>$\\Rightarrow x=4+2 \\sqrt{2}, y=1+2 \\sqrt{2}$\n\n<br/><br/>Area of $A M N B$\n\n<br/><br/>$=\\frac{1}{2}(4+4 \\sqrt{2})(4+2 \\sqrt{2}-(2+2 \\sqrt{2}))$\n\n<br/><br/>$=4(1+\\sqrt{2})$",
    "section": "A",
    "type": "SCQ"
  },
  {
    "id": "1l589r0yu",
    "questionNumber": 68,
    "questionText": "<p>Let C be a circle passing through the points A(2, $$-$$1) and B(3, 4). The line segment AB s not a diameter of C. If r is the radius of C and its centre lies on the circle $${(x - 5)^2} + {(y - 1)^2} = {{13} \\over 2}$$, then r<sup>2</sup> is equal to :</p>",
    "options": [
      "32",
      "$${{65} \\over 2}$$",
      "$${{61} \\over 2}$$",
      "30"
    ],
    "correctOption": 1,
    "correctAnswer": null,
    "questionType": "MCQ",
    "marks": 4,
    "negativeMarks": -1,
    "subject": "Mathematics",
    "topic": "family-of-circle",
    "difficulty": "medium",
    "solution": "<p>Equation of perpendicular bisector of AB is</p>\n<p>$$y - {3 \\over 2} =  - {1 \\over 5}\\left( {x - {5 \\over 2}} \\right) \\Rightarrow x + 5y = 10$$</p>\n<p>Solving it with equation of given circle,</p>\n<p>$${(x - 5)^2}{\\left( {{{10 - x} \\over 5} - 1} \\right)^2} = {{13} \\over 2}$$</p>\n<p>$$ \\Rightarrow {(x - 5)^2}\\left( {1 + {1 \\over {25}}} \\right) = {{13} \\over 2}$$</p>\n<p>$$ \\Rightarrow x - 5 =  \\pm \\,{5 \\over 2} \\Rightarrow x = {5 \\over 2}$$ or $${{15} \\over 2}$$</p>\n<p>But $$x \\ne {5 \\over 2}$$ because AB is not the diameter.</p>\n<p>So, centre will be $$\\left( {{{15} \\over 2},{1 \\over 2}} \\right)$$</p>\n<p>Now, $${r^2} = {\\left( {{{15} \\over 2} - 2} \\right)^2} + {\\left( {{1 \\over 2} + 1} \\right)^2}$$</p>\n<p>$$ = {{65} \\over 2}$$</p>",
    "section": "A",
    "type": "SCQ"
  },
  {
    "id": "NDpPPI6KPUzk1c1oIm1kmm35609",
    "questionNumber": 62,
    "questionText": "Let S<sub>1</sub> : x<sup>2</sup> + y<sup>2</sup> = 9 and S<sub>2</sub> : (x $$-$$ 2)<sup>2</sup> + y<sup>2</sup> = 1. Then the locus of center of a variable circle S which touches S<sub>1</sub> internally and S<sub>2</sub> externally always passes through the points :",
    "options": [
      "$$\\left( {{1 \\over 2}, \\pm {{\\sqrt 5 } \\over 2}} \\right)$$",
      "(1, $$\\pm$$ 2)",
      "$$\\left( {2, \\pm {3 \\over 2}} \\right)$$",
      "(0, $$\\pm$$ $$\\sqrt 3 $$)"
    ],
    "correctOption": 2,
    "correctAnswer": null,
    "questionType": "MCQ",
    "marks": 4,
    "negativeMarks": -1,
    "subject": "Mathematics",
    "topic": "family-of-circle",
    "difficulty": "medium",
    "solution": "S<sub>1</sub> : x<sup>2</sup> + y<sup>2</sup> = 9 ; C<sub>1</sub> (0, 0), r<sub>1</sub> = 3<br><br>S<sub>2</sub> : (x $$-$$ 2)<sup>2</sup> + y<sup>2</sup> = 1 ; C<sub>2</sub> (2, 0), r<sub>2</sub> = 1<br><br>Image<br><br>Let the variable circle S and its radius is r units.<br><br>Here S and S<sub>1</sub> touches internally<br><br>$$ \\therefore $$ Distance between center,<br><br>S + S<sub>1</sub> = PC<sub>1</sub> = 3 $$-$$ r<br><br>Here S and S<sub>2</sub> touches externally <br><br>$$ \\therefore $$ Distance between center,<br><br> S + S<sub>2</sub> = PC<sub>2</sub> = 1 + r<br><br>$$ \\therefore $$ PC<sub>1</sub> + PC<sub>2</sub> = 4 &gt; C<sub>1</sub> C<sub>2</sub><br><br>So locus is ellipse whose focii are C<sub>1</sub> &amp; C<sub>2</sub> and major axis is 2a = 4 and 2ae = C<sub>1</sub>C<sub>2</sub> = 2<br><br>$$ \\Rightarrow $$ $$e = {1 \\over 2}$$<br><br>$$ \\Rightarrow $$ $${b^2} = 4\\left( {1 - {1 \\over 4}} \\right) = 3$$<br><br>Centre of ellipse is midpoint of C<sub>1</sub> &amp; C<sub>2</sub> is (1, 0)<br><br>Equation of ellipse is $${{{{(x - 1)}^2}} \\over {{2^2}}} + {{{y^2}} \\over {{{\\left( {\\sqrt 3 } \\right)}^2}}} = 1$$<br><br>Now by cross checking the option $$\\left( {2, \\pm {3 \\over 2}} \\right)$$ satisfied it.",
    "section": "A",
    "type": "SCQ"
  },
  {
    "id": "1krrorbwe",
    "questionNumber": 65,
    "questionText": "Let r<sub>1</sub> and r<sub>2</sub> be the radii of the largest and smallest circles, respectively, which pass through the point ($$-$$4, 1) and having their centres on the circumference of the circle x<sup>2</sup> + y<sup>2</sup> + 2x + 4y $$-$$ 4 = 0. If $${{{r_1}} \\over {{r_2}}} = a + b\\sqrt 2 $$, then a + b is equal to :",
    "options": [
      "3",
      "11",
      "5",
      "7"
    ],
    "correctOption": 2,
    "correctAnswer": null,
    "questionType": "MCQ",
    "marks": 4,
    "negativeMarks": -1,
    "subject": "Mathematics",
    "topic": "family-of-circle",
    "difficulty": "medium",
    "solution": "<picture><source media=\"(max-width: 320px)\" srcset=\"https://imagex.cdn..net/1krswbkhm/5ed965b9-096c-45b0-bf12-4f6233af061c/0397c4b0-f29c-11eb-acf8-3bc8cc707b2f/file-1krswbkhn-320w.jpeg\"><source media=\"(max-width: 500px)\" srcset=\"https://imagex.cdn..net/1krswbkhm/5ed965b9-096c-45b0-bf12-4f6233af061c/0397c4b0-f29c-11eb-acf8-3bc8cc707b2f/file-1krswbkhn-500w.jpeg\"><source media=\"(max-width: 680px)\" srcset=\"https://imagex.cdn..net/1krswbkhm/5ed965b9-096c-45b0-bf12-4f6233af061c/0397c4b0-f29c-11eb-acf8-3bc8cc707b2f/file-1krswbkhn-680w.jpeg\"></picture> <br><br>Centre of smallest circle is A<br><br>Centre of largest circle is B<br><br>$${r_2} = |CP - CA| = 3\\sqrt 2  - 3$$<br><br>$${r_1} = CP - CB = 3\\sqrt 2  + 3$$<br><br>$${{{r_1}} \\over {{r_2}}} = {{3\\sqrt 2  + 3} \\over {3\\sqrt 2  - 3}} = {{{{(3\\sqrt 2  + 3)}^2}} \\over 9} = {(\\sqrt 2  + 1)^2} = 3 + 2\\sqrt 2 $$<br><br>a = 3, b = 2",
    "section": "A",
    "type": "SCQ"
  },
  {
    "id": "1kteov0d4",
    "questionNumber": 82,
    "questionText": "Let the equation x<sup>2</sup> + y<sup>2</sup> + px + (1 $$-$$ p)y + 5 = 0 represent circles of varying radius r $$\\in$$ (0, 5]. Then the number of elements in the set S = {q : q = p<sup>2</sup> and q is an integer} is __________.",
    "options": [],
    "correctOption": 0,
    "correctAnswer": null,
    "questionType": "NUMERICAL",
    "marks": 4,
    "negativeMarks": -1,
    "subject": "Mathematics",
    "topic": "family-of-circle",
    "difficulty": "hard",
    "solution": "$$r = \\sqrt {{{{p^2}} \\over 4} + {{{{(1 - p)}^2}} \\over 4} - 5}  = {{\\sqrt {2{p^2} - 2p - 19} } \\over 2}$$<br><br>Since, $$r \\in (0,5]$$<br><br>So, $$0 &lt; 2{p^2} - 2p - 19 \\le 100$$<br><br>$$ \\Rightarrow p \\in \\left[ {{{1 - \\sqrt {239} } \\over 2},{{1 - \\sqrt {39} } \\over 2}} \\right) \\cup \\left( {{{1 + \\sqrt {39} } \\over 2},{{1 + \\sqrt {239} } \\over 2}} \\right]$$ <br><br>so, number of integral values of p<sup>2</sup> is 61.",
    "section": "B",
    "type": "NUMERICAL"
  },
  {
    "id": "1kudyarzz",
    "questionNumber": 40,
    "questionText": "Consider a triangle $$\\Delta$$ whose two sides lie on the x-axis and the line x + y + 1 = 0. If the orthocenter of $$\\Delta$$ is (1, 1), then the equation of the circle passing through the vertices of the triangle $$\\Delta$$ is ",
    "options": [
      "x<sup>2</sup> + y<sup>2</sup> $$-$$ 3x + y = 0",
      "x<sup>2</sup> + y<sup>2</sup> + x + 3y = 0",
      "x<sup>2</sup> + y<sup>2</sup> + 2y $$-$$ 1 = 0",
      "x<sup>2</sup> + y<sup>2</sup> + x + y = 0"
    ],
    "correctOption": 1,
    "correctAnswer": null,
    "questionType": "MCQ",
    "marks": 4,
    "negativeMarks": -1,
    "subject": "Mathematics",
    "topic": "family-of-circle",
    "difficulty": "medium",
    "solution": "Equation of circle passing through C(0, 0) is <br><br>x<sup>2</sup> + y<sup>2</sup> + 2gx + 2fy = 0 ..... (i)<br><br>Since Eq. (i), also passes through ($$-$$1, 0) and (1, $$-$$2).<br><br>  <br>Then, 1 $$-$$ 2g = 0 $$\\Rightarrow$$ g = 1 / 2<br><br>and 5 + 1 $$-$$ 4f = 0 $$\\Rightarrow$$ f = 3 / 2<br><br>$$\\therefore$$ Equation of circumcircle is x<sup>2</sup> + y<sup>2</sup> + 2 $$\\times$$ $${1 \\over 2}$$x + 2 $$\\times$$ $${3 \\over 2}$$y = 0<br><br>i.e. x<sup>2</sup> + y<sup>2</sup> + x + 3y = 0",
    "section": "Sec 1",
    "instruction": "",
    "type": "SCQ"
  },
  {
    "id": "1kufffly9",
    "questionNumber": 47,
    "questionText": "Consider the region R = {(x, y) $$\\in$$ R $$\\times$$ R : x $$\\ge$$ 0 and y<sup>2</sup> $$\\le$$ 4 $$-$$ x}. Let F be the family of all circles that are contained in R and have centers on the x-axis. Let C be the circle that has largest radius among the circles in F. Let ($$\\alpha$$, $$\\beta$$) be a point where the circle C meets the curve y<sup>2</sup> = 4 $$-$$ x.<br><br>The radius of the circle C is ___________.",
    "options": [],
    "correctOption": 0,
    "correctAnswer": null,
    "questionType": "MCQ",
    "marks": 4,
    "negativeMarks": -1,
    "subject": "Mathematics",
    "topic": "family-of-circle",
    "difficulty": "medium",
    "solution": "Given, x $$\\ge$$ 0, y<sup>2</sup> $$\\le$$ 4 $$-$$ x<br><br>Let equation of circle be<br><br>(x $$-$$ h)<sup>2</sup> + y<sup>2</sup> = h<sup>2</sup> .... (i)<br><br>  <br>Solving Eq. (i) with y<sup>2</sup> = 4 $$-$$ x, we get<br><br>x<sup>2</sup> $$-$$ 2hx + 4 $$-$$ x = 0<br><br>$$\\Rightarrow$$ x<sup>2</sup> $$-$$ x(2h + 1) + 4 = 0 .... (ii)<br><br>For touching/tangency, Discriminant (D) = 0<br><br>i.e. (2h + 1)<sup>2</sup> = 16 $$\\Rightarrow$$ 2h + 1 = $$\\pm$$ 4<br><br>$$\\Rightarrow$$ 2h = $$\\pm$$ 4 $$-$$ 1<br><br>$$\\Rightarrow$$ $$h = {3 \\over 2},h = {{ - 5} \\over 2}$$ (Rejected) because part of circle lies outside R. So, $$h = {3 \\over 2}$$ = radius of circle (C).",
    "section": "Sec 2",
    "instruction": "",
    "type": "SUBJECTIVE"
  },
  {
    "id": "1kuffgfsn",
    "questionNumber": 48,
    "questionText": "Consider the region R = {(x, y) $$\\in$$ R $$\\times$$ R : x $$\\ge$$ 0 and y<sup>2</sup> $$\\le$$ 4 $$-$$ x}. Let F be the family of all circles that are contained in R and have centers on the x-axis. Let C be the circle that has largest radius among the circles in F. Let ($$\\alpha$$, $$\\beta$$) be a point where the circle C meets the curve y<sup>2</sup> = 4 $$-$$ x.<br><br>The value of $$\\alpha$$ is ___________.",
    "options": [],
    "correctOption": 0,
    "correctAnswer": null,
    "questionType": "NUMERICAL",
    "marks": 4,
    "negativeMarks": -1,
    "subject": "Mathematics",
    "topic": "family-of-circle",
    "difficulty": "hard",
    "solution": "Given, x $$\\ge$$ 0, y<sup>2</sup> $$\\le$$ 4 $$-$$ x<br><br>Let equation of circle be<br><br>(x $$-$$ h)<sup>2</sup> + y<sup>2</sup> = h<sup>2</sup> .... (i)<br><br>  <br>Solving Eq. (i) with y<sup>2</sup> = 4 $$-$$ x, we get<br><br>x<sup>2</sup> $$-$$ 2hx + 4 $$-$$ x = 0<br><br>$$\\Rightarrow$$ x<sup>2</sup> $$-$$ x(2h + 1) + 4 = 0 .... (ii)<br><br>For touching/tangency, Discriminant (D) = 0<br><br>i.e. (2h + 1)<sup>2</sup> = 16 $$\\Rightarrow$$ 2h + 1 = $$\\pm$$ 4<br><br>$$\\Rightarrow$$ 2h = $$\\pm$$ 4 $$-$$ 1<br><br>$$\\Rightarrow$$ $$h = {3 \\over 2},h = {{ - 5} \\over 2}$$ (Rejected) because part of circle lies outside R. So, $$h = {3 \\over 2}$$ = radius of circle (c).<br><br>Putting h = 3/2 in Eq. (ii),<br><br>x<sup>2</sup> $$-$$ 4x + 4 = 0 $$\\Rightarrow$$ (x $$-$$ 2)<sup>2</sup> = 0 $$\\Rightarrow$$ x = 2<br><br>So, $$\\alpha$$ = 2",
    "section": "Sec 2",
    "instruction": "",
    "type": "NUMERICAL"
  },
  {
    "id": "aLcjY2vZwkdplfoJYSjgy2xukfakl6kz",
    "questionNumber": 54,
    "questionText": "The circle passing through the intersection of the circles, <br>x<sup>2</sup> + y<sup>2</sup> – 6x = 0 and x<sup>2</sup> + y<sup>2</sup> – 4y = 0, having its centre on<br> the line, 2x – 3y + 12 = 0, also passes through the point :\n",
    "options": [
      "(–3, 1)",
      "(1, –3) ",
      "(–1, 3) ",
      "(–3, 6) "
    ],
    "correctOption": 3,
    "correctAnswer": null,
    "questionType": "MCQ",
    "marks": 4,
    "negativeMarks": -1,
    "subject": "Mathematics",
    "topic": "family-of-circle",
    "difficulty": "medium",
    "solution": "Let S be the circle passing through point of intersection of S<sub>1</sub> &amp; S<sub>2</sub><br><br>$$ \\therefore $$ S = S<sub>1</sub> + $$\\lambda $$S<sub>2</sub> = 0<br><br>$$ \\Rightarrow $$ $$S:({x^2} + {y^2} - 6x) + \\lambda ({x^2} + {y^2} - 4y) = 0$$<br><br>$$ \\Rightarrow $$ $$S:{x^2} + {y^2} - \\left( {{6 \\over {1 + \\lambda }}} \\right)x - \\left( {{{4\\lambda } \\over {1 + \\lambda }}} \\right)y = 0$$ ....(1)<br><br>Centre $$\\left( {{3 \\over {1 + \\lambda }},{{2\\lambda } \\over {1 + \\lambda }}} \\right)$$ lies on<br><br>$$2x - 3y + 12 = 0 \\Rightarrow \\lambda  =  - 3$$<br><br>put in $$(1) \\Rightarrow S:{x^2} + {y^2} + 3x - 6y = 0$$<br><br>Now check options point $$( - 3,6)$$<br><br>lies on S.",
    "section": "A",
    "type": "SCQ"
  },
  {
    "id": "KCwGH1e7nkaCmpz92Q3rsa0w2w9jx1ytgcp",
    "questionNumber": 67,
    "questionText": "The locus of the centres of the circles, which touch the circle, x<sup>2</sup>\n + y<sup>2</sup>\n = 1 externally, also touch the y-axis and\nlie in the first quadrant, is :",
    "options": [
      "$$x = \\sqrt {1 + 2y} ,y \\ge 0$$",
      "$$y = \\sqrt {1 + 2x} ,x \\ge 0$$",
      "$$y = \\sqrt {1 + 4x} ,x \\ge 0$$",
      "$$x = \\sqrt {1 + 4y} ,y \\ge 0$$"
    ],
    "correctOption": 1,
    "correctAnswer": null,
    "questionType": "MCQ",
    "marks": 4,
    "negativeMarks": -1,
    "subject": "Mathematics",
    "topic": "family-of-circle",
    "difficulty": "medium",
    "solution": "Let the centre is (h, k) &amp; radius is h (h, k &gt; 0)<br><br>\nOP = h + 1<br><br>\n<br>\n$$\\sqrt {{h^2} + {k^2}}  = h + 1$$<br><br>\n$$ \\Rightarrow {h^2} + {k^2} = {h^2} + 2h + 1$$<br><br>\n$$ \\Rightarrow {k^2} = 2h + 1$$<br><br>\n$$ \\therefore $$ Locus is y<sup>2</sup> = 2x + 1",
    "section": "A",
    "type": "SCQ"
  },
  {
    "id": "S19NaXGqv0LGnFkd1wovy",
    "questionNumber": 67,
    "questionText": "If a circle C passing through the point (4, 0) touches the circle x<sup>2</sup> + y<sup>2</sup> + 4x – 6y = 12 externally at the point (1, – 1), then the radius of C is :",
    "options": [
      "5",
      "2$$\\sqrt {5} $$",
      "4",
      "$$\\sqrt {37} $$"
    ],
    "correctOption": 0,
    "correctAnswer": null,
    "questionType": "MCQ",
    "marks": 4,
    "negativeMarks": -1,
    "subject": "Mathematics",
    "topic": "family-of-circle",
    "difficulty": "medium",
    "solution": "x<sup>2</sup> + y<sup>2</sup> + 4x $$-$$ 6y $$-$$ 12 = 0\n<br><br>Equation of tangent at (1, $$-$$ 1)\n<br><br>x $$-$$ y + 2(x + 1) $$-$$ 3(y $$-$$ 1) $$-$$ 12 = 0\n<br><br>3x $$-$$ 4y $$-$$ 7 = 0\n<br><br>$$ \\therefore $$&nbsp;&nbsp;&nbsp;Equation of circle is \n<br><br>(x<sup>2</sup> + y<sup>2</sup> + 4x $$-$$ 6y $$-$$ 12)  + $$\\lambda $$ (3x $$-$$ 4y $$-$$ 7) = 0\n<br><br>It passes through (4, 0) :\n<br><br>(16 + 16 $$-$$ 12) + $$\\lambda $$ (12 $$-$$ 7) = 0\n<br><br>$$ \\Rightarrow $$&nbsp;&nbsp;20 + $$\\lambda $$(5) = 0\n<br><br>$$ \\Rightarrow $$&nbsp;&nbsp;$$\\lambda $$ = $$-$$ 4\n<br><br>$$ \\therefore $$&nbsp;&nbsp;(x<sup>2</sup> + y<sup>2</sup> + 4x $$-$$ 6y $$-$$ 12) $$-$$ 4(3x $$-$$ 4y $$-$$ 7) = 0\n<br><br>or  &nbsp;&nbsp;x<sup>2</sup> + y<sup>2</sup> $$-$$ 8x + 10y + 16 = 0\n<br><br>Radius = $$\\sqrt {16 + 25 - 16}  = 5$$",
    "section": "A",
    "type": "SCQ"
  },
  {
    "id": "GhHPQJZMreFqETJ1UGuYQ",
    "questionNumber": 66,
    "questionText": "Three circles of radii a, b, c (a &lt; b &lt; c) touch each other externally.  If they have x-axis as a common tangent, then :",
    "options": [
      "a, b, c are in A.P.",
      "$$\\sqrt a ,\\sqrt b ,\\sqrt c $$ are in A.P",
      "$${1 \\over {\\sqrt b }}  + {1 \\over {\\sqrt c }}$$ = $${1 \\over {\\sqrt a }}$$",
      "$${1 \\over {\\sqrt b }} = {1 \\over {\\sqrt a }} + {1 \\over {\\sqrt c }}$$"
    ],
    "correctOption": 2,
    "correctAnswer": null,
    "questionType": "MCQ",
    "marks": 4,
    "negativeMarks": -1,
    "subject": "Mathematics",
    "topic": "family-of-circle",
    "difficulty": "medium",
    "solution": "<br><br>AB = AC + CB\n<br><br>$$\\sqrt {{{\\left( {b + c} \\right)}^2} - {{\\left( {c - b} \\right)}^2}} $$ = $$\\sqrt {{{\\left( {b + a} \\right)}^2} - {{\\left( {b - a} \\right)}^2}} $$ \n<br>&nbsp;&nbsp;&nbsp;&nbsp;&nbsp;&nbsp;&nbsp;&nbsp;&nbsp;&nbsp;&nbsp;&nbsp;&nbsp;&nbsp;&nbsp;&nbsp;&nbsp;&nbsp;&nbsp;&nbsp;&nbsp;&nbsp;+ $$\\sqrt {{{\\left( {c + a} \\right)}^2} - {{\\left( {c - a} \\right)}^2}} $$\n<br><br>$$ \\Rightarrow $$&nbsp;&nbsp;$$\\sqrt {2bc} $$ = $$\\sqrt {2ac} $$ + $$\\sqrt {2ab} $$\n<br><br>Dividing by $$\\sqrt {abc} $$ we get.\n<br><br>$$ \\Rightarrow $$&nbsp;&nbsp;$${1 \\over {\\sqrt a }}$$ = $${1 \\over {\\sqrt b }}$$ + $${1 \\over {\\sqrt c }}$$",
    "section": "A",
    "type": "SCQ"
  },
  {
    "id": "DtjBungYu7lolDmmqPBQA",
    "questionNumber": 67,
    "questionText": "A circle passes through the points (2, 3) and (4, 5). If its centre lies on the line, $$y - 4x + 3 = 0,$$ then its radius is equal to : ",
    "options": [
      "2",
      "$$\\sqrt 5 $$",
      "$$\\sqrt 2 $$",
      "1"
    ],
    "correctOption": 0,
    "correctAnswer": null,
    "questionType": "MCQ",
    "marks": 4,
    "negativeMarks": -1,
    "subject": "Mathematics",
    "topic": "family-of-circle",
    "difficulty": "medium",
    "solution": "Centre $(\\alpha, \\beta)$ lies on line $y-4 x+3=0$\n<br/><br/>Then, $\\quad \\beta=4 \\alpha-3$\n<br/><br/>And\n<br/><br/>$$\n\\text { Radius }=\\sqrt{(\\alpha-2)^2+(\\beta-3)^2}=\\sqrt{(\\alpha-4)^2+(\\beta-5)^2}\n$$\n<br/><br/>$$\n\\begin{aligned}\n& \\alpha^2+\\beta^2+ 13-4 \\alpha-6 \\beta=\\alpha^2+\\beta^2+41-8 \\alpha-10 \\beta \\\\\\\\\n& 4 \\alpha+4 \\beta=28 \\Rightarrow \\alpha+\\beta=7 \\\\\\\\\n& \\Rightarrow \\alpha+4 \\alpha-3=7 \\\\\\\\\n& \\Rightarrow \\alpha=2, \\beta=5\n\\end{aligned}\n$$\n<br/><br/>Therefore, $\\quad$ Radius $=\\sqrt{(2-2)^2+(5-3)^2}=2$",
    "section": "A",
    "type": "SCQ"
  },
  {
    "id": "pdGMim6mel1wVHfj",
    "questionNumber": 67,
    "questionText": "The centres of those circles which touch the circle, $${x^2} + {y^2} - 8x - 8y - 4 = 0$$, externally and also touch the $$x$$-axis, lie on :",
    "options": [
      "a circle ",
      "an ellipse which is not a circle ",
      "a hyperbola",
      "a parabola "
    ],
    "correctOption": 3,
    "correctAnswer": null,
    "questionType": "MCQ",
    "marks": 4,
    "negativeMarks": -1,
    "subject": "Mathematics",
    "topic": "family-of-circle",
    "difficulty": "medium",
    "solution": "<br><br>For the given circle, \n<br><br>center : $$(4,4)$$ \n<br><br>radius $$=6$$ \n<br><br>$$6 + k = \\sqrt {{{\\left( {h - 4} \\right)}^2} + {{\\left( {k - 4} \\right)}^2}} $$ \n<br><br>$${\\left( {h - 4} \\right)^2} = 20k + 20$$\n<br><br>$$\\therefore$$ locus of $$(h, k)$$ is \n<br><br>$${\\left( {h - 4} \\right)^2} = 20\\left( {y + 1} \\right),$$ \n<br><br>which is parabola.",
    "section": "A",
    "type": "SCQ"
  },
  {
    "id": "CVivCukoCBuAkUMw",
    "questionNumber": 66,
    "questionText": "If $$P$$ and $$Q$$ are the points of intersection of the circles \n<br>$${x^2} + {y^2} + 3x + 7y + 2p - 5 = 0$$ and $${x^2} + {y^2} + 2x + 2y - {p^2} = 0$$ then there is a circle passing through $$P,Q $$ and $$(1, 1)$$ for :",
    "options": [
      "all except one value of $$p$$ ",
      "all except two values of $$p$$ ",
      "exactly one value of $$p$$ ",
      "all values of $$p$$"
    ],
    "correctOption": 0,
    "correctAnswer": null,
    "questionType": "MCQ",
    "marks": 4,
    "negativeMarks": -1,
    "subject": "Mathematics",
    "topic": "family-of-circle",
    "difficulty": "medium",
    "solution": "The given circles are \n<br><br>$${S_1} \\equiv {x^2} + {y^2} + 3x + 7y + 2p - 5 = 0\\,\\,\\,\\,\\,\\,\\,\\,\\,\\,...\\left( 1 \\right)$$\n<br><br>$${S_2} \\equiv {x^2} + {y^2} + 2x + 2y - {p^2} = 0\\,\\,\\,\\,\\,\\,\\,\\,\\,\\,\\,\\,\\,\\,\\,\\,...\\left( 2 \\right)$$\n<br><br>$$\\therefore$$ Equation of common chord $$PQ$$ is $${S_1} - {S_2} = 0$$\n<br><br>$$ \\Rightarrow L \\equiv x + 5y + {p^2} + 2p - 5 = 0$$\n<br><br>$$ \\Rightarrow $$ Equation of circle passing through $$P$$ and $$Q$$ is \n<br><br>$${S_1} + \\lambda \\,\\,L = 0$$\n<br><br>$$ \\Rightarrow \\left( {{x^2} + {y^2} + 3x + 7y + 2p - 5} \\right) + \\lambda $$\n<br><br>$$\\left( {x + 5y + {p^2} + 2p - 5} \\right) = 0$$\n<br><br>As it passes through $$\\left( {1,1} \\right),$$ therefore\n<br><br>$$ \\Rightarrow \\left( {7 + 2p} \\right) + \\lambda \\left( {2p + {p^2} + 1} \\right) = 0$$\n<br><br>$$ \\Rightarrow \\lambda  =  - {{2p + 7} \\over {\\left( {p + 1} \\right)}},$$ \n<br><br>which does not exist for $$p=-1$$",
    "section": "A",
    "type": "SCQ"
  },
  {
    "id": "W5qdG7lPRwsgI7vI",
    "questionNumber": 77,
    "questionText": "The differential equation of the family of circles with fixed radius $$5$$ units and centre on the line $$y = 2$$ is :",
    "options": [
      "$$\\left( {x - 2} \\right){y^2} = 25 - {\\left( {y - 2} \\right)^2}$$ ",
      "$$\\left( {y - 2} \\right){y^2} = 25 - {\\left( {y - 2} \\right)^2}$$",
      "$${\\left( {y - 2} \\right)^2}{y^2} = 25 - {\\left( {y - 2} \\right)^2}$$ ",
      "$${\\left( {x - 2} \\right)^2}{y^2} = 25 - {\\left( {y - 2} \\right)^2}$$"
    ],
    "correctOption": 2,
    "correctAnswer": null,
    "questionType": "MCQ",
    "marks": 4,
    "negativeMarks": -1,
    "subject": "Mathematics",
    "topic": "family-of-circle",
    "difficulty": "medium",
    "solution": "Let the center of the circle be $$(h, 2)$$\n<br><br>$$\\therefore$$ Equation of circle is \n<br><br>$${\\left( {x - h} \\right)^2} + \\left( {y - 2} \\right){}^2 = 25\\,\\,\\,\\,\\,\\,\\,\\,\\,...\\left( 1 \\right)$$\n<br><br>Differentiating with respect to $$x,$$ we get \n<br><br>$$2\\left( {x - h} \\right) + 2\\left( {y - 2} \\right){{dy} \\over {dx}} = 0$$\n<br><br>$$ \\Rightarrow x - h =  - \\left( {y - 2} \\right){{dy} \\over {dx}}$$\n<br><br>Substituting in equation $$(1)$$ we get\n<br><br>$${\\left( {y - 2} \\right)^2}{\\left( {{{dy} \\over {dx}}} \\right)^2} + {\\left( {y - 2} \\right)^2} = 25$$\n<br><br>$$ \\Rightarrow {\\left( {y - 2} \\right)^2}{\\left( {y'} \\right)^2} = 25 - {\\left( {y - 2} \\right)^2}$$",
    "section": "A",
    "type": "SCQ"
  },
  {
    "id": "uxc61AnvgIDOB2bO",
    "questionNumber": 90,
    "questionText": "Consider a family of circles which are passing through the point $$(-1, 1)$$ and are tangent to $$x$$-axis. If $$(h, k)$$ are the coordinate of the centre of the circles, then the set of values of $$k$$ is given by the interval :",
    "options": [
      "$$ - {1 \\over 2} \\le k \\le {1 \\over 2}$$ ",
      "$$k \\le {1 \\over 2}$$ ",
      "$$0 \\le k \\le {1 \\over 2}$$ ",
      "$$k \\ge {1 \\over 2}$$ "
    ],
    "correctOption": 3,
    "correctAnswer": null,
    "questionType": "MCQ",
    "marks": 4,
    "negativeMarks": -1,
    "subject": "Mathematics",
    "topic": "family-of-circle",
    "difficulty": "medium",
    "solution": "Equation of circle whose center is $$\\left( {h,k} \\right)$$\n<br><br>i.e $${\\left( {x - h} \\right)^2} + {\\left( {y - k} \\right)^2} = {k^2}$$\n<br><br> \n<br><br>(radius of circle $$=k$$ because circle is tangent to $$x$$-axis) \n<br><br>Equation of circle passing through $$\\left( { - 1, + 1} \\right)$$\n<br><br>$$\\therefore$$ $${\\left( { - 1, - h} \\right)^2} + {\\left( {1 - k} \\right)^2} = {k^2}$$\n<br><br>$$ \\Rightarrow 1 + {h^2} + 2h + 1 + {k^2} - 2k = {k^2}$$\n<br><br>$$ \\Rightarrow {h^2} + 2h - 2k + 2 = 0$$\n<br><br>$$D \\ge 0$$\n<br><br>$$\\therefore$$ $${\\left( 2 \\right)^2} - 4 \\times 1.\\left( { - 2k + 2} \\right) \\ge 0$$\n<br><br>$$ \\Rightarrow 4 - 4\\left( { - 2k + 2} \\right) \\ge 0$$\n<br><br>$$ \\Rightarrow 1 + 2k - 2 \\ge 0$$\n<br><br>$$ \\Rightarrow k \\ge {1 \\over 2}$$",
    "section": "A",
    "type": "SCQ"
  },
  {
    "id": "R6msSj4yWbFMiKDF",
    "questionNumber": 171,
    "questionText": "A circle touches the x-axis and also touches the circle with centre at (0, 3) and radius 2. The locus of the centre of the circle is :",
    "options": [
      "an ellipse",
      "a circle ",
      "a hyperbola ",
      "a parabola "
    ],
    "correctOption": 3,
    "correctAnswer": null,
    "questionType": "MCQ",
    "marks": 4,
    "negativeMarks": -1,
    "subject": "Mathematics",
    "topic": "family-of-circle",
    "difficulty": "medium",
    "solution": "Equation of circle with center  $$(0,3)$$ and radius $$2$$ is \n<br><br>$${x^2} + {\\left( {y - 3} \\right)^2} = 4$$\n<br><br>Let locus of the variable circle is $$\\left( {\\alpha ,\\beta } \\right)$$\n<br><br>As it  touches $$x$$-axis.\n<br><br>$$\\therefore$$ It's equation is $${\\left( {x - \\alpha } \\right)^2} + {\\left( {y + \\beta } \\right)^2} = {\\beta ^2}$$ \n<br><br>\n<br><br>Circle touch externally $$ \\Rightarrow {c_1}{c_2} = {r_1} + {r_2}$$ \n<br><br>$$\\therefore$$ $$\\sqrt {{\\alpha ^2} + {{\\left( {\\beta  - 3} \\right)}^2}}  = 2 + \\beta $$\n<br><br>$${\\alpha ^2} + {\\left( {\\beta  - 3} \\right)^2} = {\\beta ^2} + 4 + 4\\beta $$\n<br><br>$$ \\Rightarrow {\\alpha ^2} = 10\\left( {\\beta  - 1/2} \\right)$$\n<br><br>$$\\therefore$$ Locus is $${x^2} = 10\\left( {y - {1 \\over 2}} \\right)$$ which is parabola.",
    "section": "A",
    "type": "SCQ"
  },
  {
    "id": "vHVMDhgdHeB7Ln2W",
    "questionNumber": 167,
    "questionText": "A variable circle passes through the fixed point A (p, q) and touches x-axis. The locus of the other end of the diameter through A is :",
    "options": [
      "$${(y\\, - \\,q)^2} = \\,4\\,px$$ ",
      "$${(x\\, - \\,q)^2} = \\,4\\,py$$",
      "$${(y\\, - \\,p)^2} = \\,4\\,qx$$",
      "$${(x\\, - \\,p)^2} = \\,4\\,qy$$"
    ],
    "correctOption": 3,
    "correctAnswer": null,
    "questionType": "MCQ",
    "marks": 4,
    "negativeMarks": -1,
    "subject": "Mathematics",
    "topic": "family-of-circle",
    "difficulty": "medium",
    "solution": "Let the variable circle be \n<br><br>$${x^2} + {y^2} + 2gx + 2fy + c = 0\\,\\,\\,\\,\\,\\,\\,\\,\\,\\,...\\left( 1 \\right)$$ \n<br><br>$$\\therefore$$ $${p^2} + {q^2} + 2gp + 2fq + c = 0\\,\\,\\,\\,\\,\\,\\,\\,\\,...\\left( 2 \\right)$$\n<br><br>Circle $$(1)$$ touches $$x$$-axis, \n<br><br>$$\\therefore$$ $${g^2} - c = 0 \\Rightarrow c = {g^2}.\\,\\,\\,$$\n<br><br>From $$(2)$$ \n<br><br>$${p^2} + {q^2} + 2gp + 2fq + {g^2} = 0\\,\\,\\,\\,\\,\\,\\,\\,\\,...\\left( 3 \\right)$$\n<br><br>Let the other end of diameter through $$(p,q)$$ be $$(h,k),$$\n<br><br>then, $${{h + p} \\over 2} =  - g$$ and $${{k + q} \\over 2} =  - f$$ \n<br><br>Put in $$(3)$$ \n<br><br>$${p^2} + {q^2} + 2p\\left( { - {{h + p} \\over 2}} \\right) + 2q\\left( { - {{k + q} \\over 2}} \\right) + {\\left( {{{h + p} \\over 2}} \\right)^2} = 0$$\n<br><br>$$ \\Rightarrow {h^2} + {p^2} - 2hp - 4kq = 0$$\n<br><br>$$\\therefore$$ locus of $$\\left( {h,k} \\right)$$ is $${x^2} + {p^2} - 2xp - 4yq = 0$$\n<br><br>$$ \\Rightarrow {\\left( {x - p} \\right)^2} = 4qy$$",
    "section": "A",
    "type": "SCQ"
  },
  {
    "id": "9LotZu5LbanRuKpm",
    "questionNumber": 160,
    "questionText": "The centres of a set of circles, each of radius 3, lie on the circle $${x^2}\\, + \\,{y^2} = 25$$. The locus of any point in the set is :",
    "options": [
      "$$4\\, \\le \\,\\,{x^2}\\, + \\,{y^2}\\, \\le \\,\\,64$$ ",
      "$${x^2}\\, + \\,{y^2}\\, \\le \\,\\,25$$ ",
      "$${x^2}\\, + \\,{y^2}\\, \\ge \\,\\,25$$ ",
      "$$3\\, \\le \\,\\,{x^2}\\, + \\,{y^2}\\, \\le \\,\\,9$$ "
    ],
    "correctOption": 0,
    "correctAnswer": null,
    "questionType": "MCQ",
    "marks": 4,
    "negativeMarks": -1,
    "subject": "Mathematics",
    "topic": "family-of-circle",
    "difficulty": "medium",
    "solution": "For any point $$P(x,y)$$ in the given circle, \n<br><br>\n<br><br>we should have \n<br><br>$$OA \\le OP \\le OB$$\n<br><br>$$ \\Rightarrow \\left( {5 - 3} \\right) \\le \\sqrt {{x^2} + {y^2}}  \\le 5 + 3$$\n<br><br>$$ \\Rightarrow 4 \\le {x^2} + {y^2} \\le 64$$",
    "section": "A",
    "type": "SCQ"
  }
]