[
  {
    "id": "1lgsykyp6",
    "questionNumber": 43,
    "questionText": "<p>Which hydride among the following is less stable?</p>",
    "options": [
      "NH$$_3$$",
      "HF",
      "LiH",
      "BeH$$_2$$"
    ],
    "correctOption": 3,
    "correctAnswer": null,
    "questionType": "MCQ",
    "marks": 4,
    "negativeMarks": -1,
    "subject": "Chemistry",
    "topic": "hydrides",
    "difficulty": "easy",
    "solution": "<p>The stability of hydrides depends on their bonding and the electronegativity difference between the elements. The greater the electronegativity difference, the more stable the hydride. Based on this, the order of stability of the given hydrides is:</p>\n<p>HF &gt; NH$$_3$$ &gt; LiH &gt; BeH$$_2$$</p>\n<p>Therefore, the less stable hydride among the given options is BeH$$_2$$.</p>\n",
    "section": "A",
    "type": "MCQ"
  },
  {
    "id": "1lgrkancd",
    "questionNumber": 42,
    "questionText": "<p>Match List I with List II</p>\n<p><style type=\"text/css\">\n.tg  {border-collapse:collapse;border-spacing:0;}\n.tg td{border-color:black;border-style:solid;border-width:1px;font-family:Arial, sans-serif;font-size:14px;\n  overflow:hidden;padding:10px 5px;word-break:normal;}\n.tg th{border-color:black;border-style:solid;border-width:1px;font-family:Arial, sans-serif;font-size:14px;\n  font-weight:normal;overflow:hidden;padding:10px 5px;word-break:normal;}\n.tg .tg-c3ow{border-color:inherit;text-align:center;vertical-align:top}\n.tg .tg-7btt{border-color:inherit;font-weight:bold;text-align:center;vertical-align:top}\n.tg .tg-0pky{border-color:inherit;text-align:left;vertical-align:top}\n</style>\n<table class=\"tg\" style=\"undefined;table-layout: fixed; width: 529px\">\n<colgroup>\n<col style=\"width: 48px\">\n<col style=\"width: 159px\">\n<col style=\"width: 52px\">\n<col style=\"width: 270px\">\n</colgroup>\n<thead>\n  <tr>\n    <th class=\"tg-7btt\"></th>\n    <th class=\"tg-7btt\">LIST I<br>Type of Hydride</th>\n    <th class=\"tg-7btt\"></th>\n    <th class=\"tg-7btt\">LIST II<br>Example</th>\n  </tr>\n</thead>\n<tbody>\n  <tr>\n    <td class=\"tg-c3ow\">A.</td>\n    <td class=\"tg-0pky\">Electron deficient hydride</td>\n    <td class=\"tg-c3ow\">I.</td>\n    <td class=\"tg-0pky\">$$\\mathrm{MgH_2}$$</td>\n  </tr>\n  <tr>\n    <td class=\"tg-c3ow\">B.</td>\n    <td class=\"tg-0pky\">Electron rich hydride</td>\n    <td class=\"tg-c3ow\">II.</td>\n    <td class=\"tg-0pky\">$$\\mathrm{HF}$$</td>\n  </tr>\n  <tr>\n    <td class=\"tg-c3ow\">C.</td>\n    <td class=\"tg-0pky\">Electron precise hydride</td>\n    <td class=\"tg-c3ow\">III.</td>\n    <td class=\"tg-0pky\">$$\\mathrm{B_2H_6}$$</td>\n  </tr>\n  <tr>\n    <td class=\"tg-c3ow\">D.</td>\n    <td class=\"tg-0pky\">Saline hydride</td>\n    <td class=\"tg-c3ow\">IV.</td>\n    <td class=\"tg-0pky\">$$\\mathrm{CH_4}$$</td>\n  </tr>\n</tbody>\n</table></p>\n<p>Choose the correct answer from the options given below:</p>",
    "options": [
      "A-III, B-II, C-I, D-IV",
      "A-II, B-III, C-I, D-IV",
      "A-III, B-II, C-IV, D-I",
      "A-II, B-III, C-IV, D-I"
    ],
    "correctOption": 2,
    "correctAnswer": null,
    "questionType": "MCQ",
    "marks": 4,
    "negativeMarks": -1,
    "subject": "Chemistry",
    "topic": "hydrides",
    "difficulty": "easy",
    "solution": "A Electron deficient hydride -> III $\\mathrm{B}_2 \\mathrm{H}_6$<br/><br/>\nB Electron rich hydride -> II $\\mathrm{HF}$<br/><br/>\nC Electron precise hydride -> IV $\\mathrm{CH}_4$<br/><br/>\nD Saline hydride -> I $\\mathrm{MgH}_2$",
    "section": "A",
    "type": "MCQ"
  },
  {
    "id": "HNVd3S1YbCv2BOjNMejgy2xukf25wpua",
    "questionNumber": 39,
    "questionText": "If the boiling point of H<sub>2</sub>O is 373 K, the boiling point of H<sub>2</sub>S will be :",
    "options": [
      "greater than 300 K but less than 373 K",
      "equal to 373 K",
      "more than 373 K",
      "less than 300 K"
    ],
    "correctOption": 3,
    "correctAnswer": null,
    "questionType": "MCQ",
    "marks": 4,
    "negativeMarks": -1,
    "subject": "Chemistry",
    "topic": "hydrides",
    "difficulty": "easy",
    "solution": "Boiling point of H<sub>2</sub>S &lt; Boiling point of H<sub>2</sub>O\n<br><br>Boiling point of H<sub>2</sub>S = 213 K",
    "section": "A",
    "type": "MCQ"
  },
  {
    "id": "KfmkbZ65PpvhypcD983rsa0w2w9jx0xwv5f",
    "questionNumber": 49,
    "questionText": "The correct statements among (a) to (d) are :\n<br>(a) saline hydrides produce H<sub>2</sub> gas when reacted with H<sub>2</sub>O.\n<br>(b) reaction of LiAlH<sub>4</sub> with BF<sub>3</sub> leads to B<sub>2</sub>H<sub>6</sub>.\n<br>(c) PH<sub>3</sub> and CH<sub>4</sub> are electron - rich and electron - precise hydrides, respectively.\n<br>(d) HF and CH<sub>4</sub> are called as molecular ",
    "options": [
      "(a), (b), (c) and (d)",
      "(a), (c) and (d) only",
      "(c) and (d) only",
      "(a), (b) and (c) only"
    ],
    "correctOption": 0,
    "correctAnswer": null,
    "questionType": "MCQ",
    "marks": 4,
    "negativeMarks": -1,
    "subject": "Chemistry",
    "topic": "hydrides",
    "difficulty": "medium",
    "solution": "(a) NaH + H<sub>2</sub>O $$ \\to $$ NaOH + H<sub>2</sub>\n<br><br>(b) 3LiAlH<sub>4</sub> + 4BF<sub>3</sub> $$ \\to $$ 2B<sub>2</sub>H<sub>6</sub> + 3LiF + 3AlF<sub>3</sub>\n<br><br>(c) PH<sub>3</sub> is electron rich due to one lone pair while CH<sub>4</sub> is electron\nprecise hydride.\n<br><br>(d) HF and CH<sub>4</sub> are molecular hydrides.",
    "section": "A",
    "type": "MCQ"
  },
  {
    "id": "OZQViQPXbBBLnjHlB8Ejp",
    "questionNumber": 46,
    "questionText": "NaH is an example of : ",
    "options": [
      "metallic hydride ",
      "saline hydride ",
      "electron-rich hydrid",
      "molecular hydride "
    ],
    "correctOption": 1,
    "correctAnswer": null,
    "questionType": "MCQ",
    "marks": 4,
    "negativeMarks": -1,
    "subject": "Chemistry",
    "topic": "hydrides",
    "difficulty": "easy",
    "solution": "NaH is an example of ionic hydride which is also known as saline hydride.",
    "section": "A",
    "type": "MCQ"
  }
]