[
  {
    "questionNumber": 86,
    "questionType": "SINGLE CORRECT",
    "text": "Which of the following is closest to the graph of $y = \\tan(\\sin x)$, $x > 0$?",
    "options": [],
    "exerciseName": "Exercise 1",
    "has_graph": true,
    "chapter": "Functions"
  },
  {
    "questionNumber": 87,
    "questionType": "SINGLE CORRECT",
    "text": "Consider the function $f : \\mathbb{R} - \\{1\\} \\to \\mathbb{R} - \\{2\\}$ given by $f(x) = \\frac{2x}{x - 1}$. Then",
    "options": [
      "$f$ is one-one but not onto",
      "$f$ is onto but not one-one",
      "$f$ is neither one-one nor onto",
      "$f$ is both one-one and onto"
    ],
    "exerciseName": "Exercise 1",
    "has_graph": false,
    "chapter": "Functions"
  },
  {
    "questionNumber": 88,
    "questionType": "SINGLE CORRECT",
    "text": "If range of function $f(x)$ whose domain is set of all real numbers is $[-2, 4]$, then range of function $g(x) = \\frac{1}{2}f(2x + 1)$ is equal to :",
    "options": [
      "$[-2, 4]$",
      "$[-1, 2]$",
      "$[-3, 9]$",
      "$[-2, 2]$"
    ],
    "exerciseName": "Exercise 1",
    "has_graph": false,
    "chapter": "Functions"
  },
  {
    "questionNumber": 89,
    "questionType": "SINGLE CORRECT",
    "text": "Let $f : \\mathbb{R} \\to \\mathbb{R}$ and $f(x) = \\frac{x(x^4 + 1)(x + 1) + x^4 + 2}{x^2 + x + 1}$, then $f(x)$ is :",
    "options": [
      "One-one, into",
      "Many one, onto",
      "One-one, onto",
      "Many one, into"
    ],
    "exerciseName": "Exercise 1",
    "has_graph": false,
    "chapter": "Functions"
  },
  {
    "questionNumber": 90,
    "questionType": "SINGLE CORRECT",
    "text": "Let $f(x)$ be defined as\n$$f(x) = \\begin{cases} |x| & 0 \\le x < 1 \\\\ |x - 1| + |x - 2| & 1 \\le x < 2 \\\\ |x - 3| & 2 \\le x < 3 \\end{cases}$$\nThe range of function $g(x) = \\sin(\\pi f(x))$ is :",
    "options": [
      "$[0, 1]$",
      "$[-1, 0]$",
      "$\\left[ -\\frac{1}{2}, \\frac{1}{2} \\right]$",
      "$[-1, 1]$"
    ],
    "exerciseName": "Exercise 1",
    "has_graph": false,
    "chapter": "Functions"
  },
  {
    "questionNumber": 91,
    "questionType": "SINGLE CORRECT",
    "text": "The number of integral values of $x$ in the domain of function $f$ defined as\n$f(x) = \\sqrt{\\ln|\\ln|x||} + \\sqrt{7|x| - |x|^2 - 10}$ is :",
    "options": [
      "5",
      "6",
      "7",
      "8"
    ],
    "exerciseName": "Exercise 1",
    "has_graph": false,
    "chapter": "Functions"
  }
]
