{
  "statusCode": 0,
  "results": [
    {
      "questionId": "bqf-mboskpfl",
      "book": "biology-xi",
      "bookGroup": "ncert",
      "chapter": "animal-kingdom",
      "chapterGroup": "zoology",
      "country": "in",
      "languages": [
        "en"
      ],
      "question": {
        "en": {
          "comprehension": null,
          "direction": null,
          "content": "In some animal groups, the body is found divided into compartments with at least some organs. This characteristic feature is called\n",
          "options": [
            {
              "identifier": "A",
              "content": " Segmentation\n"
            },
            {
              "identifier": "B",
              "content": " Metamerism\n"
            },
            {
              "identifier": "C",
              "content": " Metagenesis\n"
            },
            {
              "identifier": "D",
              "content": " Metamorphosis"
            }
          ],
          "correct_options": [
            "B"
          ],
          "answer": null,
          "explanation": "<p>Metamerism is the division of animal body, externally and internally into segments with a serial repetition of at least some organsm, e.g., annelids (earthworm).</p>\n<p>However, Segmentation refers to the division of animal's body into a series of repetitive segments. It is external in arthropods, and internal in vertebrates.</p>\n<p>Metagenesis is the phenomenon in which one generation of certain animals and plants reproduces asexually, followed by a sexually reproducing generation, i.e., alternation of generation (e.g., Obelia).</p>\n<p>Metamorphosis is the developmental process in an organism through which it changes from one life form to another (e.g., Order-Lepidoptera-Butterfly egg-larvae-pupa-adult).</p>"
        }
      },
      "section": "exemplar-questions",
      "topic": null,
      "type": "mcq",
      "user_stats": {
        "timeSpent": 18913,
        "correct": 53,
        "wrong": 47,
        "options": {
          "0": 42,
          "1": 53,
          "2": 2,
          "3": 3
        }
      }
    },
    {
      "questionId": "bqf-mboskkad",
      "book": "biology-xi",
      "bookGroup": "ncert",
      "chapter": "animal-kingdom",
      "chapterGroup": "zoology",
      "country": "in",
      "languages": [
        "en"
      ],
      "question": {
        "en": {
          "comprehension": null,
          "direction": null,
          "content": "Given below are types of cells present in some animals. Which of the following cells can differentiate to perform different functions?\n",
          "options": [
            {
              "identifier": "A",
              "content": " choanocytes\n"
            },
            {
              "identifier": "B",
              "content": " interstitial cells\n"
            },
            {
              "identifier": "C",
              "content": " gastrodermal cells\n"
            },
            {
              "identifier": "D",
              "content": " nematocytes"
            }
          ],
          "correct_options": [
            "B"
          ],
          "answer": null,
          "explanation": "<p>Interstitial cells are the totipotent cells in the body of cnidarians that are capable of giving rise to any kind of specialised cells to perform different functions.</p>\n<p>Choanocytes or collar cells are associated with filtering nutrients in sponges.</p>\n<p>Gastrodermal cells or the cnidocyst are used in attachment and defence in cnidarians.</p>\n<p>Nematocyst are capsules that are the specialised cells in cnidarians, acting as a paralysing sting and used for defence purpose.</p>"
        }
      },
      "section": "exemplar-questions",
      "topic": null,
      "type": "mcq",
      "user_stats": {
        "timeSpent": 28643,
        "correct": 29,
        "wrong": 71,
        "options": {
          "0": 35,
          "1": 29,
          "2": 16,
          "3": 20
        }
      }
    },
    {
      "questionId": "bqf-mboskogm",
      "book": "biology-xi",
      "bookGroup": "ncert",
      "chapter": "animal-kingdom",
      "chapterGroup": "zoology",
      "country": "in",
      "languages": [
        "en"
      ],
      "question": {
        "en": {
          "comprehension": null,
          "direction": null,
          "content": "Which one of the following sets of animals share a four chambered heart?\n",
          "options": [
            {
              "identifier": "A",
              "content": " Amphibian, Reptiles, Birds\n"
            },
            {
              "identifier": "B",
              "content": " Crocodiles, Birds, Mammals\n"
            },
            {
              "identifier": "C",
              "content": " Crocodiles, Lizards, Turtles\n"
            },
            {
              "identifier": "D",
              "content": " Lizards, Mammals, Birds"
            }
          ],
          "correct_options": [
            "B"
          ],
          "answer": null,
          "explanation": "<p>Crocodiles, birds, mammals have four-chambered heart.</p>\n<p>Heart is usually three chambered in reptiles with an exception crocodiles, which possess four chambered heart. The division in their heart is due to the incomplete interventricular septum, in ventricles.</p>\n<p>Heart in birds and mammals is four chambered and there is a complete division of interventricular septum in ventricles. Whereas, amphibians possess a three chambered heart in which the ventricl are not divided hence, 2 atria and one ventricle is present.</p>"
        }
      },
      "section": "exemplar-questions",
      "topic": null,
      "type": "mcq",
      "user_stats": {
        "timeSpent": 16949,
        "correct": 87,
        "wrong": 13,
        "options": {
          "0": 4,
          "1": 87,
          "2": 4,
          "3": 5
        }
      }
    },
    {
      "questionId": "bqf-mboskozy",
      "book": "biology-xi",
      "bookGroup": "ncert",
      "chapter": "animal-kingdom",
      "chapterGroup": "zoology",
      "country": "in",
      "languages": [
        "en"
      ],
      "question": {
        "en": {
          "comprehension": null,
          "direction": null,
          "content": "Which of the following pairs of animals has non-glandular skin?\n",
          "options": [
            {
              "identifier": "A",
              "content": " Snake and frog\n"
            },
            {
              "identifier": "B",
              "content": " Chameleon and turtle\n"
            },
            {
              "identifier": "C",
              "content": " Frog and pigeon\n"
            },
            {
              "identifier": "D",
              "content": " Crocodile and tiger"
            }
          ],
          "correct_options": [
            "B"
          ],
          "answer": null,
          "explanation": "<p>Chameleon and turtle belong to class-Reptilia and possess dry and non-glandular skin with scales.</p>\n<p>Frog, pigeon and tiger possess modifications in their skin according to adaptations in their respective habitats.</p>"
        }
      },
      "section": "exemplar-questions",
      "topic": null,
      "type": "mcq",
      "user_stats": {
        "timeSpent": 24941,
        "correct": 45,
        "wrong": 55,
        "options": {
          "0": 19,
          "1": 45,
          "2": 15,
          "3": 21
        }
      }
    },
    {
      "questionId": "bqf-mboskrn7",
      "book": "biology-xi",
      "bookGroup": "ncert",
      "chapter": "animal-kingdom",
      "chapterGroup": "zoology",
      "country": "in",
      "languages": [
        "en"
      ],
      "question": {
        "en": {
          "comprehension": null,
          "direction": null,
          "content": "Birds and mammals share one of the following characteristics as a common feature.\n",
          "options": [
            {
              "identifier": "A",
              "content": " Pigmented skin\n"
            },
            {
              "identifier": "B",
              "content": " Pneumatic bones\n"
            },
            {
              "identifier": "C",
              "content": " Viviparity\n"
            },
            {
              "identifier": "D",
              "content": " Warm blooded body"
            }
          ],
          "correct_options": [
            "D"
          ],
          "answer": null,
          "explanation": "<p>Warm blooded animals can maintain constant body temperature, irrespective of the surrounding environment, i.e., their body temperature is fixed. Warm blooded body is the common characteristic feature in birds and mammals. This characteristic was first evolved in higher reptiles, birds and mammals acquire this feature from higher reptiles during evolution.</p>\n<p>Pigmented skin is the adaptive feature in mammals, and is not present in birds. Pneumatic bones are found only in birds as their flight adaptation. These reduce body weight for flight. Viviparity is shown by mammals and not by birds as they are oviparous, i.e. lay eggs.</p>"
        }
      },
      "section": "exemplar-questions",
      "topic": null,
      "type": "mcq",
      "user_stats": {
        "timeSpent": 17949,
        "correct": 88,
        "wrong": 12,
        "options": {
          "0": 2,
          "1": 3,
          "2": 8,
          "3": 88
        }
      }
    },
    {
      "questionId": "bqf-mboskpjb",
      "book": "biology-xi",
      "bookGroup": "ncert",
      "chapter": "animal-kingdom",
      "chapterGroup": "zoology",
      "country": "in",
      "languages": [
        "en"
      ],
      "question": {
        "en": {
          "comprehension": null,
          "direction": null,
          "content": "Which one of the following sets of animals belong to a single taxonomic group?\n",
          "options": [
            {
              "identifier": "A",
              "content": " Cuttlefish, jellyfish, silverfish, dogfish, starfish\n"
            },
            {
              "identifier": "B",
              "content": " bat, pigeon, butterfly\n"
            },
            {
              "identifier": "C",
              "content": " Monkey, chimpanzee, man\n"
            },
            {
              "identifier": "D",
              "content": " Silkworm, tapeworm, earthworm"
            }
          ],
          "correct_options": [
            "C"
          ],
          "answer": null,
          "explanation": "<p>Monkey, chimpanzee and man belong to a single taxonomic group, i.e., mammals because all of them possess the following characters.</p>\n<p>(i) Milk producing mammary glands.</p>\n<p>(ii) Two pairs of limbs.</p>\n<p>(iii) Presence of external ears.</p>\n<p>(iv) Viviparity.</p>\n<p>(v) Skin possessing hair.</p>\n<p>Whereas,</p>\n<p><style type=\"text/css\">\n.tg  {border-collapse:collapse;border-spacing:0;}\n.tg td{border-color:black;border-style:solid;border-width:1px;font-family:Arial, sans-serif;font-size:14px;\n  overflow:hidden;padding:10px 5px;word-break:normal;}\n.tg th{border-color:black;border-style:solid;border-width:1px;font-family:Arial, sans-serif;font-size:14px;\n  font-weight:normal;overflow:hidden;padding:10px 5px;word-break:normal;}\n.tg .tg-amwm{font-weight:bold;text-align:center;vertical-align:top}\n.tg .tg-0lax{text-align:left;vertical-align:top}\n</style>\n<table class=\"tg\" style=\"undefined;table-layout: fixed; width: 471px\"><colgroup>\n<col style=\"width: 155px\">\n<col style=\"width: 316px\">\n</colgroup>\n<thead>\n  <tr>\n    <th class=\"tg-amwm\">Animal Group</th>\n    <th class=\"tg-amwm\">Taxonomic Group</th>\n  </tr></thead>\n<tbody>\n  <tr>\n    <td class=\"tg-0lax\">Cuttle fish</td>\n    <td class=\"tg-0lax\">Phylum-Mollusca, Class-Cephalopoda,</td>\n  </tr>\n  <tr>\n    <td class=\"tg-0lax\">Jelly fish</td>\n    <td class=\"tg-0lax\">Phylum-Cnidaria</td>\n  </tr>\n  <tr>\n    <td class=\"tg-0lax\">Silver fish</td>\n    <td class=\"tg-0lax\">Class-Insecta, Order-Thysanura, Phylum-Arthropoda,</td>\n  </tr>\n  <tr>\n    <td class=\"tg-0lax\">Dog fish</td>\n    <td class=\"tg-0lax\">Phylum-Chordata, Class-Chondrithyes,</td>\n  </tr>\n  <tr>\n    <td class=\"tg-0lax\">Starfish</td>\n    <td class=\"tg-0lax\">Phylum-Echinodermata, Class-Asteroidea</td>\n  </tr>\n</tbody>\n</table></p>\n<p><style type=\"text/css\">\n.tg  {border-collapse:collapse;border-spacing:0;}\n.tg td{border-color:black;border-style:solid;border-width:1px;font-family:Arial, sans-serif;font-size:14px;\n  overflow:hidden;padding:10px 5px;word-break:normal;}\n.tg th{border-color:black;border-style:solid;border-width:1px;font-family:Arial, sans-serif;font-size:14px;\n  font-weight:normal;overflow:hidden;padding:10px 5px;word-break:normal;}\n.tg .tg-amwm{font-weight:bold;text-align:center;vertical-align:top}\n.tg .tg-0lax{text-align:left;vertical-align:top}\n</style>\n<table class=\"tg\" style=\"undefined;table-layout: fixed; width: 471px\"><colgroup>\n<col style=\"width: 155px\">\n<col style=\"width: 316px\">\n</colgroup>\n<thead>\n  <tr>\n    <th class=\"tg-amwm\">Animal Group</th>\n    <th class=\"tg-amwm\">Taxonomic Group</th>\n  </tr></thead>\n<tbody>\n  <tr>\n    <td class=\"tg-0lax\">Bat</td>\n    <td class=\"tg-0lax\">Phylum-Chordata, Class-Mammalia</td>\n  </tr>\n  <tr>\n    <td class=\"tg-0lax\">Pigeon</td>\n    <td class=\"tg-0lax\">Phylum-Chordata, Class- Aves</td>\n  </tr>\n  <tr>\n    <td class=\"tg-0lax\">Butterfly</td>\n    <td class=\"tg-0lax\">Phylum-Arthropoda, Class-Insecta, Order-Lepidoptera</td>\n  </tr>\n</tbody>\n</table></p>\n<p><style type=\"text/css\">\n.tg  {border-collapse:collapse;border-spacing:0;}\n.tg td{border-color:black;border-style:solid;border-width:1px;font-family:Arial, sans-serif;font-size:14px;\n  overflow:hidden;padding:10px 5px;word-break:normal;}\n.tg th{border-color:black;border-style:solid;border-width:1px;font-family:Arial, sans-serif;font-size:14px;\n  font-weight:normal;overflow:hidden;padding:10px 5px;word-break:normal;}\n.tg .tg-amwm{font-weight:bold;text-align:center;vertical-align:top}\n.tg .tg-0lax{text-align:left;vertical-align:top}\n</style>\n<table class=\"tg\" style=\"undefined;table-layout: fixed; width: 471px\"><colgroup>\n<col style=\"width: 155px\">\n<col style=\"width: 316px\">\n</colgroup>\n<thead>\n  <tr>\n    <th class=\"tg-amwm\">Animal Group</th>\n    <th class=\"tg-amwm\">Taxonomic Group</th>\n  </tr></thead>\n<tbody>\n  <tr>\n    <td class=\"tg-0lax\">Silkworm</td>\n    <td class=\"tg-0lax\">Phylum-Arthropoda, Class-Insecta, Order-Lepidoptera</td>\n  </tr>\n  <tr>\n    <td class=\"tg-0lax\">Tapeworm</td>\n    <td class=\"tg-0lax\">Phylum-Platyhelminthes, Class- Cestoda</td>\n  </tr>\n  <tr>\n    <td class=\"tg-0lax\">Earthworm</td>\n    <td class=\"tg-0lax\">Phylum-Annelida, Class-Oligochaeta</td>\n  </tr>\n</tbody>\n</table></p>"
        }
      },
      "section": "exemplar-questions",
      "topic": null,
      "type": "mcq",
      "user_stats": {
        "timeSpent": 24154,
        "correct": 85,
        "wrong": 15,
        "options": {
          "0": 5,
          "1": 3,
          "2": 85,
          "3": 8
        }
      }
    },
    {
      "questionId": "bqf-mbosknsm",
      "book": "biology-xi",
      "bookGroup": "ncert",
      "chapter": "animal-kingdom",
      "chapterGroup": "zoology",
      "country": "in",
      "languages": [
        "en"
      ],
      "question": {
        "en": {
          "comprehension": null,
          "direction": null,
          "content": "Which one of the following statements is incorrect?\n",
          "options": [
            {
              "identifier": "A",
              "content": " Mesoglea is present in between ectoderm and endoderm in Obelia\n"
            },
            {
              "identifier": "B",
              "content": " Asterias exhibits radial symmetry an\n"
            },
            {
              "identifier": "C",
              "content": " Fasciola is a pseudocoelomate animal\n"
            },
            {
              "identifier": "D",
              "content": " Taenia is a triploblastic animal"
            }
          ],
          "correct_options": [
            "C"
          ],
          "answer": null,
          "explanation": "<p>The statement, Fasciola is a pseudocoelomate animals, is incorrect as it does not possess body cavity hence, it is an acoelomate.</p>\n<p>Mesoglea is an undifferentiated layer and is a characteristic of diploblastic and triploblastic animals present along with ectoderm and endoderm.</p>\n<p>Symmetry in which the body can be divided into two equal identical halves from any plane passing through the central axis. as shown by Asterias, is called radial symmetry Taenia is a triploblastic animal, it possesses three germinal layers, i.e., ectoderm, endoderm and mesoderm.</p>"
        }
      },
      "section": "exemplar-questions",
      "topic": null,
      "type": "mcq",
      "user_stats": {
        "timeSpent": 33949,
        "correct": 55,
        "wrong": 45,
        "options": {
          "0": 20,
          "1": 15,
          "2": 55,
          "3": 10
        }
      }
    },
    {
      "questionId": "bqf-mbosklv6",
      "book": "biology-xi",
      "bookGroup": "ncert",
      "chapter": "animal-kingdom",
      "chapterGroup": "zoology",
      "country": "in",
      "languages": [
        "en"
      ],
      "question": {
        "en": {
          "comprehension": null,
          "direction": null,
          "content": "Which one of the following statements is incorrect?\n",
          "options": [
            {
              "identifier": "A",
              "content": " In cockroaches and prawns excretion of waste material occurs through Malpighian tubules.\n"
            },
            {
              "identifier": "B",
              "content": " In ctenophores, locomotion is mediated by comb plates.\n"
            },
            {
              "identifier": "C",
              "content": " In Fasciola flame cells take part in excretion\n"
            },
            {
              "identifier": "D",
              "content": " Earthworms are hermaphrodites and yet cross fertilisation take place among them."
            }
          ],
          "correct_options": [
            "A"
          ],
          "answer": null,
          "explanation": "The statement (a) is incorrect because Malpighian tubules are excretory structures in most of the insects, including cockroach, but green glands perform excretory functions in crustaceans like prawns, whereas all the other statements are true."
        }
      },
      "section": "exemplar-questions",
      "topic": null,
      "type": "mcq",
      "user_stats": {
        "timeSpent": 37562,
        "correct": 34,
        "wrong": 66,
        "options": {
          "0": 34,
          "1": 6,
          "2": 12,
          "3": 48
        }
      }
    },
    {
      "questionId": "bqf-mbosklxc",
      "book": "biology-xi",
      "bookGroup": "ncert",
      "chapter": "animal-kingdom",
      "chapterGroup": "zoology",
      "country": "in",
      "languages": [
        "en"
      ],
      "question": {
        "en": {
          "comprehension": null,
          "direction": null,
          "content": "Which one of the following is oviparous?\n",
          "options": [
            {
              "identifier": "A",
              "content": " Platypus\n"
            },
            {
              "identifier": "B",
              "content": " Flying fox (bat)\n"
            },
            {
              "identifier": "C",
              "content": " Elephant\n"
            },
            {
              "identifier": "D",
              "content": " Whale"
            }
          ],
          "correct_options": [
            "A"
          ],
          "answer": null,
          "explanation": "Platypus is a primitive mammal which shows many characters of their reptilian descent, such as ovaparity, i.e., these lay eggs.\nRest all three animals, i.e., flying fox, elephant and whale are viviparous mammals and giving birth to young ones."
        }
      },
      "section": "exemplar-questions",
      "topic": null,
      "type": "mcq",
      "user_stats": {
        "timeSpent": 13730,
        "correct": 85,
        "wrong": 15,
        "options": {
          "0": 85,
          "1": 9,
          "2": 5,
          "3": 1
        }
      }
    },
    {
      "questionId": "bqf-mboskir9",
      "book": "biology-xi",
      "bookGroup": "ncert",
      "chapter": "animal-kingdom",
      "chapterGroup": "zoology",
      "country": "in",
      "languages": [
        "en"
      ],
      "question": {
        "en": {
          "comprehension": null,
          "direction": null,
          "content": "Which one of the following is not a poisonous snake?\n \n ",
          "options": [
            {
              "identifier": "A",
              "content": "Cobra"
            },
            {
              "identifier": "B",
              "content": " Viper\n"
            },
            {
              "identifier": "C",
              "content": " Python\n"
            },
            {
              "identifier": "D",
              "content": "Krait"
            }
          ],
          "correct_options": [
            "C"
          ],
          "answer": null,
          "explanation": "Except Python, all other snakes are highly poisonous in nature. Python due is large in size and kills its prey by constriction of their body."
        }
      },
      "section": "exemplar-questions",
      "topic": null,
      "type": "mcq",
      "user_stats": {
        "timeSpent": 12412,
        "correct": 70,
        "wrong": 30,
        "options": {
          "0": 7,
          "1": 11,
          "2": 70,
          "3": 11
        }
      }
    },
    {
      "questionId": "bqf-mboskojj",
      "book": "biology-xi",
      "bookGroup": "ncert",
      "chapter": "animal-kingdom",
      "chapterGroup": "zoology",
      "country": "in",
      "languages": [
        "en"
      ],
      "question": {
        "en": {
          "comprehension": null,
          "direction": null,
          "content": "<p>Match the following list of animals with their level of organisation.</p>\n<p><style type=\"text/css\">\n.tg  {border-collapse:collapse;border-spacing:0;}\n.tg td{border-color:black;border-style:solid;border-width:1px;font-family:Arial, sans-serif;font-size:14px;\n  overflow:hidden;padding:10px 5px;word-break:normal;}\n.tg th{border-color:black;border-style:solid;border-width:1px;font-family:Arial, sans-serif;font-size:14px;\n  font-weight:normal;overflow:hidden;padding:10px 5px;word-break:normal;}\n.tg .tg-baqh{text-align:center;vertical-align:top}\n.tg .tg-amwm{font-weight:bold;text-align:center;vertical-align:top}\n.tg .tg-0lax{text-align:left;vertical-align:top}\n</style>\n<table class=\"tg\" style=\"undefined;table-layout: fixed; width: 515px\"><colgroup>\n<col style=\"width: 71px\">\n<col style=\"width: 203px\">\n<col style=\"width: 70px\">\n<col style=\"width: 171px\">\n</colgroup>\n<thead>\n  <tr>\n    <th class=\"tg-amwm\"></th>\n    <th class=\"tg-amwm\">Division of Labour</th>\n    <th class=\"tg-amwm\"></th>\n    <th class=\"tg-amwm\">Animal</th>\n  </tr></thead>\n<tbody>\n  <tr>\n    <td class=\"tg-baqh\">(i)</td>\n    <td class=\"tg-0lax\">Organ level</td>\n    <td class=\"tg-baqh\">A.</td>\n    <td class=\"tg-0lax\">Pheretima</td>\n  </tr>\n  <tr>\n    <td class=\"tg-baqh\">(ii)</td>\n    <td class=\"tg-0lax\">Cellular aggregate level</td>\n    <td class=\"tg-baqh\">B.</td>\n    <td class=\"tg-0lax\">Fasciola</td>\n  </tr>\n  <tr>\n    <td class=\"tg-baqh\">(iii)</td>\n    <td class=\"tg-0lax\">Tissue level</td>\n    <td class=\"tg-baqh\">C.</td>\n    <td class=\"tg-0lax\">Spongilla</td>\n  </tr>\n  <tr>\n    <td class=\"tg-baqh\">(iv)</td>\n    <td class=\"tg-0lax\">Organ system level</td>\n    <td class=\"tg-baqh\">D.</td>\n    <td class=\"tg-0lax\">Obelia</td>\n  </tr>\n</tbody>\n</table></p>\n<p>Choose the correct match showing division of labour with animal example.</p>",
          "options": [
            {
              "identifier": "A",
              "content": " (i)-B, (ii)-C, (iii)-D and (iv)-A\n"
            },
            {
              "identifier": "B",
              "content": " (i)-B, (ii)-D, (iii)-C and (iv)-A\n"
            },
            {
              "identifier": "C",
              "content": " (i)-D, (ii)-A, (iii)-B and (iv)-C\n"
            },
            {
              "identifier": "D",
              "content": " (i)-A, (ii)-D, (iii)-C and (v)-B"
            }
          ],
          "correct_options": [
            "C"
          ],
          "answer": null,
          "explanation": "<p>(i)-D, (ii) - A, (iii)-B, (iv) - C</p>\n<p>Pheretima possesses organ system level of organisation.</p>\n<p>Fasciola possesses organ level organisation.</p>\n<p>Spongilla possesses cellular aggregate level organisation.</p>\n<p>Obelia possesses tissue level organisation.</p>"
        }
      },
      "section": "exemplar-questions",
      "topic": null,
      "type": "mcq",
      "user_stats": {
        "timeSpent": 35464,
        "correct": 5,
        "wrong": 95,
        "options": {
          "0": 87,
          "1": 5,
          "2": 5,
          "3": 2
        }
      }
    },
    {
      "questionId": "bqf-mboskpms",
      "book": "biology-xi",
      "bookGroup": "ncert",
      "chapter": "animal-kingdom",
      "chapterGroup": "zoology",
      "country": "in",
      "languages": [
        "en"
      ],
      "question": {
        "en": {
          "comprehension": null,
          "direction": null,
          "content": "Body cavity is the cavity present between body wall and gut wall. In some animals the body cavity is not lined by mesoderm. Such animals are called.\n",
          "options": [
            {
              "identifier": "A",
              "content": " Acoelomate\n"
            },
            {
              "identifier": "B",
              "content": " Pseudocoelomate\n"
            },
            {
              "identifier": "C",
              "content": " Coelomate\n"
            },
            {
              "identifier": "D",
              "content": " Haemocoelomate"
            }
          ],
          "correct_options": [
            "B"
          ],
          "answer": null,
          "explanation": "<p>When body cavity is not completely lined by the mesoderm instead it is present in the form of scattered pouches, in between ectoderm and endoderm, this type of body cavity called pseudocoelomate, e.g., roundworm.</p>\n<p>Acoelomates the animals in which coelom is completely absent as, e.g., flatworms.</p>\n<p>Coelomates have their body cavity lined by mesoderm and hence have true coelom, e.g., annelids, molluscs, arthropods, etc.</p>\n<p>Haemocoelomates are the animals in which body cavity is filled with haemolymph, e.g., arthropods, molluscs.</p>"
        }
      },
      "section": "exemplar-questions",
      "topic": null,
      "type": "mcq",
      "user_stats": {
        "timeSpent": 22574,
        "correct": 36,
        "wrong": 64,
        "options": {
          "0": 58,
          "1": 36,
          "2": 4,
          "3": 1
        }
      }
    },
    {
      "questionId": "bqf-mbosknvn",
      "book": "biology-xi",
      "bookGroup": "ncert",
      "chapter": "animal-kingdom",
      "chapterGroup": "zoology",
      "country": "in",
      "languages": [
        "en"
      ],
      "question": {
        "en": {
          "comprehension": null,
          "direction": null,
          "content": "<p>Match the column I with column II and choose the correct option.</p>\n<p><style type=\"text/css\">\n.tg  {border-collapse:collapse;border-spacing:0;}\n.tg td{border-color:black;border-style:solid;border-width:1px;font-family:Arial, sans-serif;font-size:14px;\n  overflow:hidden;padding:10px 5px;word-break:normal;}\n.tg th{border-color:black;border-style:solid;border-width:1px;font-family:Arial, sans-serif;font-size:14px;\n  font-weight:normal;overflow:hidden;padding:10px 5px;word-break:normal;}\n.tg .tg-baqh{text-align:center;vertical-align:top}\n.tg .tg-amwm{font-weight:bold;text-align:center;vertical-align:top}\n.tg .tg-0lax{text-align:left;vertical-align:top}\n</style>\n<table class=\"tg\" style=\"undefined;table-layout: fixed; width: 535px\"><colgroup>\n<col style=\"width: 74px\">\n<col style=\"width: 211px\">\n<col style=\"width: 73px\">\n<col style=\"width: 177px\">\n</colgroup>\n<thead>\n  <tr>\n    <th class=\"tg-amwm\"></th>\n    <th class=\"tg-amwm\">Division of Labour</th>\n    <th class=\"tg-amwm\"></th>\n    <th class=\"tg-amwm\">Animal</th>\n  </tr></thead>\n<tbody>\n  <tr>\n    <td class=\"tg-baqh\">A.</td>\n    <td class=\"tg-0lax\">Porifera</td>\n    <td class=\"tg-baqh\">1.</td>\n    <td class=\"tg-0lax\">Canal system</td>\n  </tr>\n  <tr>\n    <td class=\"tg-baqh\">B.</td>\n    <td class=\"tg-0lax\">Aschelminthes</td>\n    <td class=\"tg-baqh\">2.</td>\n    <td class=\"tg-0lax\">Water vascular system</td>\n  </tr>\n  <tr>\n    <td class=\"tg-baqh\">C.</td>\n    <td class=\"tg-0lax\">Annelida</td>\n    <td class=\"tg-baqh\">3.</td>\n    <td class=\"tg-0lax\">Muscular Pharynx</td>\n  </tr>\n  <tr>\n    <td class=\"tg-baqh\">D.</td>\n    <td class=\"tg-0lax\">Arthropoda</td>\n    <td class=\"tg-baqh\">4.</td>\n    <td class=\"tg-0lax\">Jointed appendages</td>\n  </tr>\n  <tr>\n    <td class=\"tg-baqh\">E.</td>\n    <td class=\"tg-0lax\">Echinodermata</td>\n    <td class=\"tg-baqh\">5.</td>\n    <td class=\"tg-0lax\">Metameres</td>\n  </tr>\n</tbody></table></p>",
          "options": [
            {
              "identifier": "A",
              "content": "A-2, B-3, C-5, D-4, E-1"
            },
            {
              "identifier": "B",
              "content": "A-2, B-5, C-3, D-4, E-1"
            },
            {
              "identifier": "C",
              "content": "A-1, B-3, C-5, D-4, E-2"
            },
            {
              "identifier": "D",
              "content": "A-1, B-5, C-3, D-4, E-2"
            }
          ],
          "correct_options": [
            "C"
          ],
          "answer": null,
          "explanation": "<p>The body of porifera (sponges) is organised in such a way, so that they form a complex system of pores and canals called canal system. This system helps in regulating the flow of water within them e.g., Sycon.</p>\n<p>Aschelminthes possess jointed appendages e.g., Ascaris.</p>\n<p>Annelidans possess metameric, segmentation in body e.g., earthworm.</p>\n<p>Arthropodans possess jointed appendages in each segment of their body e.g., cockrach.</p>\n<p>Echinoderms possess water vascular system or ambulacral system e.g., Asterias or starfish.</p>"
        }
      },
      "section": "exemplar-questions",
      "topic": null,
      "type": "mcq",
      "user_stats": {
        "timeSpent": 49188,
        "correct": 78,
        "wrong": 22,
        "options": {
          "0": 9,
          "1": 4,
          "2": 78,
          "3": 8
        }
      }
    },
    {
      "questionId": "bqf-mboskmfg",
      "book": "biology-xi",
      "bookGroup": "ncert",
      "chapter": "animal-kingdom",
      "chapterGroup": "zoology",
      "country": "in",
      "languages": [
        "en"
      ],
      "question": {
        "en": {
          "comprehension": null,
          "direction": null,
          "content": "Identify the phylum in which adults exhibit radial symmetry and larva exhibit bilateral symmetry.",
          "options": [],
          "correct_options": [],
          "answer": null,
          "explanation": "Symmetry is an attribute of an organism showing regularity in body parts on a plane or around an axis.\nIn Phylum Echinodermata, the adult echinoderms are radially symmetrical but the larvae are bilaterally symmetrical."
        }
      },
      "section": "exemplar-questions",
      "topic": null,
      "type": "subjective-very-short"
    },
    {
      "questionId": "bqf-mboskoln",
      "book": "biology-xi",
      "bookGroup": "ncert",
      "chapter": "animal-kingdom",
      "chapterGroup": "zoology",
      "country": "in",
      "languages": [
        "en"
      ],
      "question": {
        "en": {
          "comprehension": null,
          "direction": null,
          "content": "What is the importance of pneumatic bones and air sacs in Aves?",
          "options": [],
          "correct_options": [],
          "answer": null,
          "explanation": "Birds possess light weight bones that contain internal spaces filled with air. These are called pneumatic bones. They help in, reducing their body weight, thus is an adaptation for flight.\nAerodynamic lungs with specialised air sacs provides an additional feature and gives adaptability to birds to fly (e.g., bald eagle, pigeon)."
        }
      },
      "section": "exemplar-questions",
      "topic": null,
      "type": "subjective-very-short"
    },
    {
      "questionId": "bqf-mboskisu",
      "book": "biology-xi",
      "bookGroup": "ncert",
      "chapter": "animal-kingdom",
      "chapterGroup": "zoology",
      "country": "in",
      "languages": [
        "en"
      ],
      "question": {
        "en": {
          "comprehension": null,
          "direction": null,
          "content": "What is metagenesis? Mention an example which exhibits this phenomenon.",
          "options": [],
          "correct_options": [],
          "answer": null,
          "explanation": "Metagenesis is the phenomenon in which one generation of certain plants and animals reproduce asexually, followed by the sexually reproducing generation. Both the forms are diploid in metagenesis hence, it is the false alternation of generation.\nCoelenterates exhibits metagenesis (e.g., Obelia) where polyp form alternates with medusa in its life cycle."
        }
      },
      "section": "exemplar-questions",
      "topic": null,
      "type": "subjective-very-short"
    },
    {
      "questionId": "bqf-mboskmh0",
      "book": "biology-xi",
      "bookGroup": "ncert",
      "chapter": "animal-kingdom",
      "chapterGroup": "zoology",
      "country": "in",
      "languages": [
        "en"
      ],
      "question": {
        "en": {
          "comprehension": null,
          "direction": null,
          "content": "What is the role of feathers?",
          "options": [],
          "correct_options": [],
          "answer": null,
          "explanation": "<p>Feathers are the epidermal growth that forms distinctive outer covering or plumage in birds.</p>\n<p>Feathers play a variety of roles like</p>\n<p>(i) They help in creating airfoil shape for wings so, as to provide lift and help in flight.</p>\n<p>(ii) Feathers helps in maintaining body temperature.</p>\n<p>(iii) Feathers play a vital role in mating by providing secondary sex characters in both the sexes the colour and markings determine the attractiveness of mate.</p>"
        }
      },
      "section": "exemplar-questions",
      "topic": null,
      "type": "subjective-very-short"
    },
    {
      "questionId": "bqf-mboskn4v",
      "book": "biology-xi",
      "bookGroup": "ncert",
      "chapter": "animal-kingdom",
      "chapterGroup": "zoology",
      "country": "in",
      "languages": [
        "en"
      ],
      "question": {
        "en": {
          "comprehension": null,
          "direction": null,
          "content": "Which group of chordates possess sucking and circular mouth without jaws?",
          "options": [],
          "correct_options": [],
          "answer": null,
          "explanation": "Class-Cyclostomata is comprised of, the living jawless fishes. Their mouth is circular and lack jaws, hence they are also called agnathans. It works like a sucker and is surrounded by tentacles (e.g., lampreys and haglish). These also prosses rectroctable horny teeth."
        }
      },
      "section": "exemplar-questions",
      "topic": null,
      "type": "subjective-very-short"
    },
    {
      "questionId": "bqf-mbosknxy",
      "book": "biology-xi",
      "bookGroup": "ncert",
      "chapter": "animal-kingdom",
      "chapterGroup": "zoology",
      "country": "in",
      "languages": [
        "en"
      ],
      "question": {
        "en": {
          "comprehension": null,
          "direction": null,
          "content": "Give one example each for an animal possessing placoid scales and that with cycloid scales.",
          "options": [],
          "correct_options": [],
          "answer": null,
          "explanation": "<p>Fishes possess dermal scales, each scale made of dentine that is secreted by dermal papilla. Placoid scales are hard and microscopic in size, their body is made up of dentine and exposed surface is covered with enamel, Cycloid scales are strong and extremely flexible.</p>\n<p>They are large, oval and made up of isopectine (layer of collagenous fibre). Placoid Scales are the characteristic features of cartilaginous fishes. (e.g., Scoliodon). Whereas, cycloid scale are found in bony fishes (e.g., Catla catla).</p>"
        }
      },
      "section": "exemplar-questions",
      "topic": null,
      "type": "subjective-very-short"
    },
    {
      "questionId": "bqf-mboskj2e",
      "book": "biology-xi",
      "bookGroup": "ncert",
      "chapter": "animal-kingdom",
      "chapterGroup": "zoology",
      "country": "in",
      "languages": [
        "en"
      ],
      "question": {
        "en": {
          "comprehension": null,
          "direction": null,
          "content": "Mention two modifications in reptiles required for terrestrial mode of life.\n",
          "options": [],
          "correct_options": [],
          "answer": null,
          "explanation": "<p>There are certain characters acquired by reptiles for the terrestrial adaptations. Two of then are</p>\n<p>(i) Their body is covered by dry and cornified skin and epidermal scales or scutes.</p>\n<p>(ii) Fertilisation is internal.</p>"
        }
      },
      "section": "exemplar-questions",
      "topic": null,
      "type": "subjective-very-short"
    },
    {
      "questionId": "bqf-mboskmij",
      "book": "biology-xi",
      "bookGroup": "ncert",
      "chapter": "animal-kingdom",
      "chapterGroup": "zoology",
      "country": "in",
      "languages": [
        "en"
      ],
      "question": {
        "en": {
          "comprehension": null,
          "direction": null,
          "content": "Mention one example each for animals with chitinous exoskeleton and those covered by a calcareous shell.",
          "options": [],
          "correct_options": [],
          "answer": null,
          "explanation": "Every living form maintain a proper shape, size and structure. In multicellular lower organisms the shape of body is maintained by certain biological materials like chitin and calcium substances. Chitinous exoskeleton is the characteristic feature of arthropods. (e.g., cockroach, termite,wasp) whereas, calcareous shell is present in molluscs (gastropods). (e.g., snail and slugs)."
        }
      },
      "section": "exemplar-questions",
      "topic": null,
      "type": "subjective-very-short"
    },
    {
      "questionId": "bqf-mbosklcn",
      "book": "biology-xi",
      "bookGroup": "ncert",
      "chapter": "animal-kingdom",
      "chapterGroup": "zoology",
      "country": "in",
      "languages": [
        "en"
      ],
      "question": {
        "en": {
          "comprehension": null,
          "direction": null,
          "content": "Name the animal, which exhibits the phenomenon of bioluminescence. Mention the phylum to which it belongs.",
          "options": [],
          "correct_options": [],
          "answer": null,
          "explanation": "<p>The phenomenon of production and emission of light by an organism as a result of chemical reaction during which chemical energy is converted to light energy is called bioluminescence.</p>\n<p>Ctenoplana from phylum-Ctenophora, exhibits the phenomenon of bioluminescence.</p>"
        }
      },
      "section": "exemplar-questions",
      "topic": null,
      "type": "subjective-very-short"
    },
    {
      "questionId": "bqf-mboskp1l",
      "book": "biology-xi",
      "bookGroup": "ncert",
      "chapter": "animal-kingdom",
      "chapterGroup": "zoology",
      "country": "in",
      "languages": [
        "en"
      ],
      "question": {
        "en": {
          "comprehension": null,
          "direction": null,
          "content": "<p>Write one example for each of the following in the space provided.</p>\n<p>(a) Cold blooded animal ............</p>\n<p>(b) Warm blooded animal ..........</p>\n<p>(c) Animal possessing dry and cornified skin ............</p>\n<p>(d) Dioecious animal ..........</p>\n",
          "options": [],
          "correct_options": [],
          "answer": null,
          "explanation": "<p>(a) Crocodilus (crocodile) is a cold blooded animal.</p>\n<p>(b) Elephas maximus (elephant), (mammal) is warm blooded animal.</p>\n<p>(c) Testudo (tortoise) bears dry and cornified skin.</p>\n<p>(d) Ascaris (roundworm) is a dioecious animal.</p>"
        }
      },
      "section": "exemplar-questions",
      "topic": null,
      "type": "subjective-very-short"
    },
    {
      "questionId": "bqf-mboskj3v",
      "book": "biology-xi",
      "bookGroup": "ncert",
      "chapter": "animal-kingdom",
      "chapterGroup": "zoology",
      "country": "in",
      "languages": [
        "en"
      ],
      "question": {
        "en": {
          "comprehension": null,
          "direction": null,
          "content": "Differentiate between a diplobastic and a triploblastic animal.\n",
          "options": [],
          "correct_options": [],
          "answer": null,
          "explanation": "Animals in which the cells are arranged in two embryonic layers, an external ectoderm and an internal endoderm are called diploblastic animals (e.g., coelentrates). While those animals in which the developing embryo has a third germinal layer, i.e., mesoderm lying between the ectoderm and endoderm are called triploblastic animals. (e.g., chordates)."
        }
      },
      "section": "exemplar-questions",
      "topic": null,
      "type": "subjective-very-short"
    },
    {
      "questionId": "bqf-mboskrpz",
      "book": "biology-xi",
      "bookGroup": "ncert",
      "chapter": "animal-kingdom",
      "chapterGroup": "zoology",
      "country": "in",
      "languages": [
        "en"
      ],
      "question": {
        "en": {
          "comprehension": null,
          "direction": null,
          "content": "<p>Give an example of the following</p>\n<p>(a) Roundworm</p>\n<p>(b) Fish possessing poison sting</p>\n<p>(c) A limbless reptile/amphibian</p>\n<p>(d) An oviparous mammal</p>",
          "options": [],
          "correct_options": [],
          "answer": null,
          "explanation": "<p>(a) Roundworm - Ascaris</p>\n<p>(b) Fish possessing poison sting - Trygon</p>\n<p>(c) A limbless reptile/amphibian - Ichthyophis</p>\n<p>(d) An oviparous mammal - Duck billed platypus.</p>"
        }
      },
      "section": "exemplar-questions",
      "topic": null,
      "type": "subjective-very-short"
    },
    {
      "questionId": "bqf-mboskiuk",
      "book": "biology-xi",
      "bookGroup": "ncert",
      "chapter": "animal-kingdom",
      "chapterGroup": "zoology",
      "country": "in",
      "languages": [
        "en"
      ],
      "question": {
        "en": {
          "comprehension": null,
          "direction": null,
          "content": "<p>Provide appropriate technical term in the space provided.</p>\n<p>(a) Blood-filled cavity in arthropods ............</p>\n<p>(b) Free-floating form of cnidaria .............</p>\n<p>(c) Stinging organ of jelly fishes .............</p>\n<p>(d) Lateral appendages in aquatic annelids ...........</p>",
          "options": [],
          "correct_options": [],
          "answer": null,
          "explanation": "<p>(a) Haemocoel is the blood-filled cavity in arthropods containing haemolymph.</p>\n<p>(b) Medusa is a form in cnidarians in which the body is shaped like an umbrella which can float freely in sed water</p>\n<p>(c) Nematocytes are capsules of specialised cells in cnidarians which act as a paralysing sting.</p>\n<p>(d) Parapodia are the paired unjointed lateral outgrowth in annelids bearing chaetae.</p>"
        }
      },
      "section": "exemplar-questions",
      "topic": null,
      "type": "subjective-very-short"
    },
    {
      "questionId": "bqf-mboskkcq",
      "book": "biology-xi",
      "bookGroup": "ncert",
      "chapter": "animal-kingdom",
      "chapterGroup": "zoology",
      "country": "in",
      "languages": [
        "en"
      ],
      "question": {
        "en": {
          "comprehension": null,
          "direction": null,
          "content": "<p>Match the following.</p>\n<p><style type=\"text/css\">\n.tg  {border-collapse:collapse;border-spacing:0;}\n.tg td{border-color:black;border-style:solid;border-width:1px;font-family:Arial, sans-serif;font-size:14px;\n  overflow:hidden;padding:10px 5px;word-break:normal;}\n.tg th{border-color:black;border-style:solid;border-width:1px;font-family:Arial, sans-serif;font-size:14px;\n  font-weight:normal;overflow:hidden;padding:10px 5px;word-break:normal;}\n.tg .tg-c3ow{border-color:inherit;text-align:center;vertical-align:top}\n.tg .tg-7btt{border-color:inherit;font-weight:bold;text-align:center;vertical-align:top}\n.tg .tg-0pky{border-color:inherit;text-align:left;vertical-align:top}\n</style>\n<table class=\"tg\" style=\"undefined;table-layout: fixed; width: 488px\"><colgroup>\n<col style=\"width: 74px\">\n<col style=\"width: 164px\">\n<col style=\"width: 73px\">\n<col style=\"width: 177px\">\n</colgroup>\n<thead>\n  <tr>\n    <th class=\"tg-7btt\"></th>\n    <th class=\"tg-7btt\">Animals</th>\n    <th class=\"tg-7btt\"></th>\n    <th class=\"tg-7btt\">Locomotory Organ</th>\n  </tr></thead>\n<tbody>\n  <tr>\n    <td class=\"tg-c3ow\">A.</td>\n    <td class=\"tg-0pky\">Octopus</td>\n    <td class=\"tg-c3ow\">1.</td>\n    <td class=\"tg-0pky\">Limbs</td>\n  </tr>\n  <tr>\n    <td class=\"tg-c3ow\">B.</td>\n    <td class=\"tg-0pky\">Crocodile</td>\n    <td class=\"tg-c3ow\">2.</td>\n    <td class=\"tg-0pky\">Comb plates</td>\n  </tr>\n  <tr>\n    <td class=\"tg-c3ow\">C.</td>\n    <td class=\"tg-0pky\">Catta</td>\n    <td class=\"tg-c3ow\">3.</td>\n    <td class=\"tg-0pky\">Tentacles</td>\n  </tr>\n  <tr>\n    <td class=\"tg-c3ow\">D.</td>\n    <td class=\"tg-0pky\">Ctenoplana</td>\n    <td class=\"tg-c3ow\">4.</td>\n    <td class=\"tg-0pky\">Fins</td>\n  </tr>\n</tbody>\n</table></p>\n\n",
          "options": [],
          "correct_options": [],
          "answer": null,
          "explanation": "<p>A. $\\rightarrow$ (iii)\nB. $\\rightarrow$ (i)\nC. $\\rightarrow$ (iv)\nD. $\\rightarrow$ (ii)</p>\n<p>(a) Octopus Tentacles are the appendages in invertebrates that are used for grasping food and for locomotion.</p>\n<p.(b) Crocodile Limbs are used for locomotion, and swimming.</p>\n<p>(c) Catta Fins Fins are means of locomotion and are used to generate optimum thrust thus controlling the subsequent motion.</p>\n<p>(d) Ctenoplana Comb plates are locomotory organs formed by strong cilia with fused bases.</p>"
        }
      },
      "section": "exemplar-questions",
      "topic": null,
      "type": "subjective-very-short"
    },
    {
      "questionId": "bqf-mboskn76",
      "book": "biology-xi",
      "bookGroup": "ncert",
      "chapter": "animal-kingdom",
      "chapterGroup": "zoology",
      "country": "in",
      "languages": [
        "en"
      ],
      "question": {
        "en": {
          "comprehension": null,
          "direction": null,
          "content": "<p>Differentiate between</p>\n<p>(a) Open circulatory system and closed circulatary system.</p>\n<p>(b) Oviparous and viviparous characteristic .</p>\n<p>(c) Direct development and Indirect development.</p>",
          "options": [],
          "correct_options": [],
          "answer": null,
          "explanation": "<p>Differentiation between these are as below</p>\n<p><style type=\"text/css\">\n.tg  {border-collapse:collapse;border-spacing:0;}\n.tg td{border-color:black;border-style:solid;border-width:1px;font-family:Arial, sans-serif;font-size:14px;\n  overflow:hidden;padding:10px 5px;word-break:normal;}\n.tg th{border-color:black;border-style:solid;border-width:1px;font-family:Arial, sans-serif;font-size:14px;\n  font-weight:normal;overflow:hidden;padding:10px 5px;word-break:normal;}\n.tg .tg-1wig{font-weight:bold;text-align:left;vertical-align:top}\n.tg .tg-baqh{text-align:center;vertical-align:top}\n.tg .tg-amwm{font-weight:bold;text-align:center;vertical-align:top}\n.tg .tg-0lax{text-align:left;vertical-align:top}\n</style>\n<table class=\"tg\" style=\"undefined;table-layout: fixed; width: 591px\"><colgroup>\n<col style=\"width: 77px\">\n<col style=\"width: 261px\">\n<col style=\"width: 253px\">\n</colgroup>\n<thead>\n  <tr>\n    <th class=\"tg-amwm\">(a)</th>\n    <th class=\"tg-1wig\">Open Circulatory System</th>\n    <th class=\"tg-1wig\">Closed Circulatory System</th>\n  </tr></thead>\n<tbody>\n  <tr>\n    <td class=\"tg-baqh\"></td>\n    <td class=\"tg-0lax\">In this type of circulation, blood flows in spaces called sinuses and the cells and tissues are directly bathed in it.<br>e.g., arthropods (grasshopper, cockroach), gastropods (snail).</td>\n    <td class=\"tg-0lax\">In this type of circulation, blood is circulated via a series of vessels (arteries, veins and capillaries).<br>e.g., annelids (earthworm) and vertebrates (birds, primates etc).</td>\n  </tr>\n  <tr>\n    <td class=\"tg-amwm\">(b)</td>\n    <td class=\"tg-1wig\">Oviparous characteristics Animals</td>\n    <td class=\"tg-1wig\">Viviparous Characteristic Animals</td>\n  </tr>\n  <tr>\n    <td class=\"tg-baqh\"></td>\n    <td class=\"tg-0lax\">Oviparity is expulsion of undeveloped eggs rather than live young ones<br>Animals that lay eggs. are called oviparous.<br>e.g., fishes, reptiles, amphibians, birds, in sects and monotremes (mammals that lay eggs).</td>\n    <td class=\"tg-0lax\">Viviparity is retention and growth of fertilised egg within the material body until the young one is capable of independent existence.<br>Animals which give birth to their young ones and are called viviparous animals. e.g., mammals.</td>\n  </tr>\n  <tr>\n    <td class=\"tg-amwm\">(c)</td>\n    <td class=\"tg-1wig\">Direct Development</td>\n    <td class=\"tg-1wig\">Indirect Development</td>\n  </tr>\n  <tr>\n    <td class=\"tg-baqh\"></td>\n    <td class=\"tg-0lax\">Direct development is the type of development in which there is no larval/nymphal or other intermediate stages in life, cycle between the egg (or birth) and the adult (e.g., mammals)</td>\n    <td class=\"tg-0lax\">Indirect development is mostly observed in lower animals. The adult individuals lay eggs, which develop passing into the adult after passing through few to several larval nymphal stages. (e.g., echinoderms, arthropods)</td>\n  </tr>\n</tbody></table></p>"
        }
      },
      "section": "exemplar-questions",
      "topic": null,
      "type": "subjective-short"
    },
    {
      "questionId": "bqf-mboskonk",
      "book": "biology-xi",
      "bookGroup": "ncert",
      "chapter": "animal-kingdom",
      "chapterGroup": "zoology",
      "country": "in",
      "languages": [
        "en"
      ],
      "question": {
        "en": {
          "comprehension": null,
          "direction": null,
          "content": "Sort out the animals on the basis of their symmetry (radial or bilateral) coelenterates, ctenophores, annelids, arthropods and echinoderms.",
          "options": [],
          "correct_options": [],
          "answer": null,
          "explanation": "<p>Body symmetry is the similarity of body parts in different region and directions of the body plan.</p>\n<p>In radial symmetry, body of an individual can be divided into equal halves by any plans passing through the longitudinal axis. (e.g., Coelentrates, Ctenophores, Echinoderms.</p>\n<p>In bilateral symmetry, body can be divided into two equal halves when the plane passes through the median longitudnal or saggital axis. (e.g., Annelids, Arthropods)</p>\n<p><img src=\"https://app-content.cdn.examgoal.net/fly/@width/image/jaoe38c1mbt3le89/8c432b8e-e95f-4b81-805a-8d9d729a7411/91f88390-4764-11f0-9e4e-ff535330d4b4/file-jaoe38c1mbt3le8a.webp?format=webp\" data-orsrc=\"https://app-content.cdn.examgoal.net/image/jaoe38c1mbt3le89/8c432b8e-e95f-4b81-805a-8d9d729a7411/91f88390-4764-11f0-9e4e-ff535330d4b4/file-jaoe38c1mbt3le8a.webp\" loading=\"lazy\" style=\"max-width: 100%;height: auto;display: block;margin: 0 auto;max-height: 40vh;vertical-align: baseline\"></p>"
        }
      },
      "section": "exemplar-questions",
      "topic": null,
      "type": "subjective-short"
    },
    {
      "questionId": "bqf-mboskrsd",
      "book": "biology-xi",
      "bookGroup": "ncert",
      "chapter": "animal-kingdom",
      "chapterGroup": "zoology",
      "country": "in",
      "languages": [
        "en"
      ],
      "question": {
        "en": {
          "comprehension": null,
          "direction": null,
          "content": "There has been an increase in the number of chambers in heart during evolution of vertebrates. Give the names of the class of vertebrates having two, three or four chambered heart.",
          "options": [],
          "correct_options": [],
          "answer": null,
          "explanation": "<p>(a) Two chambered heart is present in organisms like fishes. Only one atria and one ventricle is present which are not separated and hence mixing of oxygenated and deoxygenated blood blood occurs.</p>\n<p>(b) Three chambered heart develops after the division of auricle into right and left halves as in amphibian. Mixing of oxygenated and deoxygenated blood occurs in ventricles.</p>\n<p>(c) An intermidiary heart is present in reptiles in which ventricle get partially divided through a septum which is incomplete. e.g., Crocodiles, thus having four-chambered heart.</p>\n<p>(d) In four chambered heart both the auricle and ventricle are divided into two halves and thus no mixing of oxgyenated and deoxygenated blood occurs. e.g., birds and mammals.</p>\n<p><img src=\"https://app-content.cdn.examgoal.net/fly/@width/image/jaoe38c1mbt3ohck/69c6a7c3-49ad-462f-ad5f-36ec8cb3187e/e7ced940-4764-11f0-9e4e-ff535330d4b4/file-jaoe38c1mbt3ohcl.webp?format=webp\" data-orsrc=\"https://app-content.cdn.examgoal.net/image/jaoe38c1mbt3ohck/69c6a7c3-49ad-462f-ad5f-36ec8cb3187e/e7ced940-4764-11f0-9e4e-ff535330d4b4/file-jaoe38c1mbt3ohcl.webp\" loading=\"lazy\" style=\"max-width: 100%;height: auto;display: block;margin: 0 auto;max-height: 40vh;vertical-align: baseline\"></p>"
        }
      },
      "section": "exemplar-questions",
      "topic": null,
      "type": "subjective-short"
    },
    {
      "questionId": "bqf-mbosknao",
      "book": "biology-xi",
      "bookGroup": "ncert",
      "chapter": "animal-kingdom",
      "chapterGroup": "zoology",
      "country": "in",
      "languages": [
        "en"
      ],
      "question": {
        "en": {
          "comprehension": null,
          "direction": null,
          "content": "<p>Fill up the blank spaces appropriately</p>\n<p><style type=\"text/css\">\n.tg  {border-collapse:collapse;border-spacing:0;}\n.tg td{border-color:black;border-style:solid;border-width:1px;font-family:Arial, sans-serif;font-size:14px;\n  overflow:hidden;padding:10px 5px;word-break:normal;}\n.tg th{border-color:black;border-style:solid;border-width:1px;font-family:Arial, sans-serif;font-size:14px;\n  font-weight:normal;overflow:hidden;padding:10px 5px;word-break:normal;}\n.tg .tg-amwm{font-weight:bold;text-align:center;vertical-align:top}\n.tg .tg-0lax{text-align:left;vertical-align:top}\n</style>\n<table class=\"tg\" style=\"undefined;table-layout: fixed; width: 608px\"><colgroup>\n<col style=\"width: 124px\">\n<col style=\"width: 165px\">\n<col style=\"width: 135px\">\n<col style=\"width: 184px\">\n</colgroup>\n<thead>\n  <tr>\n    <th class=\"tg-amwm\">Phylum/Class</th>\n    <th class=\"tg-amwm\">Excretory Organ</th>\n    <th class=\"tg-amwm\">Circulatory Organ</th>\n    <th class=\"tg-amwm\">Respiratory Organ</th>\n  </tr></thead>\n<tbody>\n  <tr>\n    <td class=\"tg-0lax\">Arthropoda</td>\n    <td class=\"tg-0lax\"></td>\n    <td class=\"tg-0lax\"></td>\n    <td class=\"tg-0lax\">Lungs/Gills/Tracheal System</td>\n  </tr>\n  <tr>\n    <td class=\"tg-0lax\"></td>\n    <td class=\"tg-0lax\">Nephridia</td>\n    <td class=\"tg-0lax\">Closed</td>\n    <td class=\"tg-0lax\">Skin/Parapodia</td>\n  </tr>\n  <tr>\n    <td class=\"tg-0lax\"></td>\n    <td class=\"tg-0lax\">Metanephridia</td>\n    <td class=\"tg-0lax\">Open</td>\n    <td class=\"tg-0lax\"></td>\n  </tr>\n  <tr>\n    <td class=\"tg-0lax\">Amphibia</td>\n    <td class=\"tg-0lax\"></td>\n    <td class=\"tg-0lax\">Closed</td>\n    <td class=\"tg-0lax\">Lung</td>\n  </tr>\n</tbody>\n</table></p>",
          "options": [],
          "correct_options": [],
          "answer": null,
          "explanation": "<p>Excretion involves the elimination of metabolic waste products from the animal body.</p>\n<p>Different organs are involved in the process of excretion in different animals.</p>\n<p>(a) In Arthropods, the Malpighian tubules remove excretory products from haemolymph.</p>\n<p>(b) In Annelids, the excretory organ occurs as segmentally arranged coiled tubules called nephridia</p>\n<p>(c) In Molluscas, excretion occurs by paired structures called organ of Bojanus also called metanephridia.</p>\n<p>(d) In Amphibians mesonephric kidneys are associated with excretion.</p>\n<p>Blood circulation involves the circulation of blood and lymph along with oxygen, carbondioxide, hormones, blood cells, etc, within the body system for the nourishment of cells, fighting diseases, and for stabilising body temperature and pH .</p>\n<p><style type=\"text/css\">\n.tg  {border-collapse:collapse;border-spacing:0;}\n.tg td{border-color:black;border-style:solid;border-width:1px;font-family:Arial, sans-serif;font-size:14px;\n  overflow:hidden;padding:10px 5px;word-break:normal;}\n.tg th{border-color:black;border-style:solid;border-width:1px;font-family:Arial, sans-serif;font-size:14px;\n  font-weight:normal;overflow:hidden;padding:10px 5px;word-break:normal;}\n.tg .tg-amwm{font-weight:bold;text-align:center;vertical-align:top}\n.tg .tg-0lax{text-align:left;vertical-align:top}\n</style>\n<table class=\"tg\" style=\"undefined;table-layout: fixed; width: 408px\"><colgroup>\n<col style=\"width: 206px\">\n<col style=\"width: 202px\">\n</colgroup>\n<thead>\n  <tr>\n    <th class=\"tg-amwm\">Open Circulation</th>\n    <th class=\"tg-amwm\">Closed Circulation</th>\n  </tr></thead>\n<tbody>\n  <tr>\n    <td class=\"tg-0lax\">In this, blood is pumped out of the heart into sinuses which directly open into cells and tissues, e.g., phylum-Arthropoda, and Mollusca.</td>\n    <td class=\"tg-0lax\">In this system, blood is circulated through a series of complexly arranged vessels and capillaries e.g., phylum-Annelida and Class-Amphibia.</td>\n  </tr>\n</tbody>\n</table></p>\n<p>Respiratory organs are involved in the exchange of gases from the atmosphere. Different respiratory organs are as follows</p>\n<p>(a) Lungs/gills/tracheal system in arthropoda and molluscs.</p>\n<p>(b) Skin in annelids.</p>\n<p>(c) Lungs and skin in amphibians.</p>"
        }
      },
      "section": "exemplar-questions",
      "topic": null,
      "type": "subjective-short"
    },
    {
      "questionId": "bqf-mboskndz",
      "book": "biology-xi",
      "bookGroup": "ncert",
      "chapter": "animal-kingdom",
      "chapterGroup": "zoology",
      "country": "in",
      "languages": [
        "en"
      ],
      "question": {
        "en": {
          "comprehension": null,
          "direction": null,
          "content": "<p>Match the following</p>\n<p><style type=\"text/css\">\n.tg  {border-collapse:collapse;border-spacing:0;}\n.tg td{border-color:black;border-style:solid;border-width:1px;font-family:Arial, sans-serif;font-size:14px;\n  overflow:hidden;padding:10px 5px;word-break:normal;}\n.tg th{border-color:black;border-style:solid;border-width:1px;font-family:Arial, sans-serif;font-size:14px;\n  font-weight:normal;overflow:hidden;padding:10px 5px;word-break:normal;}\n.tg .tg-baqh{text-align:center;vertical-align:top}\n.tg .tg-0lax{text-align:left;vertical-align:top}\n</style>\n<table class=\"tg\" style=\"undefined;table-layout: fixed; width: 546px\"><colgroup>\n<col style=\"width: 77px\">\n<col style=\"width: 157px\">\n<col style=\"width: 82px\">\n<col style=\"width: 230px\">\n</colgroup>\n<thead>\n  <tr>\n    <th class=\"tg-baqh\">A.</th>\n    <th class=\"tg-0lax\">Amphibia</th>\n    <th class=\"tg-baqh\">(i)</th>\n    <th class=\"tg-0lax\">Air bladder</th>\n  </tr></thead>\n<tbody>\n  <tr>\n    <td class=\"tg-baqh\">B.</td>\n    <td class=\"tg-0lax\">Mammals</td>\n    <td class=\"tg-baqh\">(ii)</td>\n    <td class=\"tg-0lax\">Cartilaginous notochord</td>\n  </tr>\n  <tr>\n    <td class=\"tg-baqh\">C.</td>\n    <td class=\"tg-0lax\">Chondrichthyes</td>\n    <td class=\"tg-baqh\">(iii)</td>\n    <td class=\"tg-0lax\">Mammary glands</td>\n  </tr>\n  <tr>\n    <td class=\"tg-baqh\">D.</td>\n    <td class=\"tg-0lax\">Osteichthyes</td>\n    <td class=\"tg-baqh\">(iv)</td>\n    <td class=\"tg-0lax\">Pneumatic bones</td>\n  </tr>\n  <tr>\n    <td class=\"tg-baqh\">E.</td>\n    <td class=\"tg-0lax\">Cyclostomata</td>\n    <td class=\"tg-baqh\">(v)</td>\n    <td class=\"tg-0lax\">Dual habitat</td>\n  </tr>\n  <tr>\n    <td class=\"tg-baqh\">F.</td>\n    <td class=\"tg-0lax\">Aves</td>\n    <td class=\"tg-baqh\">(vi)</td>\n    <td class=\"tg-0lax\">Sucking and circular mouth with out jaws.</td>\n  </tr>\n</tbody></table></p>",
          "options": [],
          "correct_options": [],
          "answer": null,
          "explanation": "<p>A. $\\rightarrow$ (v)\nB. $\\rightarrow$ (iii)\nC. $\\rightarrow$ (ii)\nD. $\\rightarrow$ (i)\nE. $\\rightarrow$ (vi)\nF. $\\rightarrow$ (iv)</p>\n<p>A. Amphibians possess dual habitat, i.e., they are found in both aquatic and terrestrial habitat. Their larva is completely aquatic and adult lives in terrestrial as well as in aquatic habitat</p>\n<p>B. Mammals have mammary glands which produce milk and feed their young ones. The mammary glands are enlarged exocrine modified sweat glands functional in female mammals.</p>\n<p>C. Chondrichthyes have the cartilaginous rod (notochord) in the young stage which is gradually replaced by cartilage.</p>\n<p>D. Osteichthyes have air bladder which is a vesicle or sac containing air,</p>\n<p>E. Cyclostomes possess sucking and circular mouth without jaws which is surrounded by tentacles and the tongue bears teeth. e.g., lamprey and nagfish.</p>\n<p>F. Aves have light weighted bones with internal spaces filled with air called pneumatic bones and aerodynamic lungs with specialised air sacs. These are the adaptations which enable birds to fly.</p>"
        }
      },
      "section": "exemplar-questions",
      "topic": null,
      "type": "subjective-short"
    },
    {
      "questionId": "bqf-mboskjqw",
      "book": "biology-xi",
      "bookGroup": "ncert",
      "chapter": "animal-kingdom",
      "chapterGroup": "zoology",
      "country": "in",
      "languages": [
        "en"
      ],
      "question": {
        "en": {
          "comprehension": null,
          "direction": null,
          "content": "Endoparasites are found inside the host body. Mention the special structure, possessed by these and which enables them to survive in those conditions.",
          "options": [],
          "correct_options": [],
          "answer": null,
          "explanation": "<p>The endoparasites such as Taenia solium and Fasciola hepatica (liver fluke), etc., are found inside the host body, and survive due to the presence of certain characters.</p>\n<p>Special characters present in by endoparasites are as folows</p>\n<p>(i) The possess anaerobic respiration and the gaseous exchange is through general body surface.</p>\n<p>(ii) These organisms bear additional organ for the attachment to the host. Fasciola hepatica possesses acetabulum or posterior sucker for the attachment. Taenia solium posses hooks and suckers for the attachment with the host.</p>\n<p>(iii) Reproductive organs are well developed. They are generally, hermaphrodite and self fertilisation is common in them.</p>\n<p>(iv) The thick tegument (body covering) is present which is resistant to the host's digestive enzymes and antitoxins.</p>\n<p>(v) Absence of locomotary organs.</p>\n<p>(vi) Tapeworms lack digestive organs because digested and semidigested food of the host is directly absorbed through their because body surface.</p>"
        }
      },
      "section": "exemplar-questions",
      "topic": null,
      "type": "subjective-short"
    },
    {
      "questionId": "bqf-mboskoqa",
      "book": "biology-xi",
      "bookGroup": "ncert",
      "chapter": "animal-kingdom",
      "chapterGroup": "zoology",
      "country": "in",
      "languages": [
        "en"
      ],
      "question": {
        "en": {
          "comprehension": null,
          "direction": null,
          "content": "<p>Match the following and write correct choice in space provided</p>\n<p><style type=\"text/css\">\n.tg  {border-collapse:collapse;border-spacing:0;}\n.tg td{border-color:black;border-style:solid;border-width:1px;font-family:Arial, sans-serif;font-size:14px;\n  overflow:hidden;padding:10px 5px;word-break:normal;}\n.tg th{border-color:black;border-style:solid;border-width:1px;font-family:Arial, sans-serif;font-size:14px;\n  font-weight:normal;overflow:hidden;padding:10px 5px;word-break:normal;}\n.tg .tg-baqh{text-align:center;vertical-align:top}\n.tg .tg-amwm{font-weight:bold;text-align:center;vertical-align:top}\n.tg .tg-0lax{text-align:left;vertical-align:top}\n</style>\n<table class=\"tg\" style=\"undefined;table-layout: fixed; width: 565px\"><colgroup>\n<col style=\"width: 80px\">\n<col style=\"width: 162px\">\n<col style=\"width: 85px\">\n<col style=\"width: 238px\">\n</colgroup>\n<thead>\n  <tr>\n    <th class=\"tg-baqh\"></th>\n    <th class=\"tg-amwm\">Animal</th>\n    <th class=\"tg-baqh\"></th>\n    <th class=\"tg-amwm\">Characteristics</th>\n  </tr></thead>\n<tbody>\n  <tr>\n    <td class=\"tg-baqh\">A.</td>\n    <td class=\"tg-0lax\">Pila</td>\n    <td class=\"tg-baqh\">(i)</td>\n    <td class=\"tg-0lax\">Jointed appendages</td>\n  </tr>\n  <tr>\n    <td class=\"tg-baqh\">B.</td>\n    <td class=\"tg-0lax\">Cockroach</td>\n    <td class=\"tg-baqh\">(ii)</td>\n    <td class=\"tg-0lax\">Perching</td>\n  </tr>\n  <tr>\n    <td class=\"tg-baqh\">C.</td>\n    <td class=\"tg-0lax\">Asterias</td>\n    <td class=\"tg-baqh\">(iii)</td>\n    <td class=\"tg-0lax\">Water vascular system</td>\n  </tr>\n  <tr>\n    <td class=\"tg-baqh\">D.</td>\n    <td class=\"tg-0lax\">Torpedo</td>\n    <td class=\"tg-baqh\">(iv)</td>\n    <td class=\"tg-0lax\">Electric organ</td>\n  </tr>\n  <tr>\n    <td class=\"tg-baqh\">E.</td>\n    <td class=\"tg-0lax\">Parrot</td>\n    <td class=\"tg-baqh\">(v)</td>\n    <td class=\"tg-0lax\">Presence of shell</td>\n  </tr>\n  <tr>\n    <td class=\"tg-baqh\">F.</td>\n    <td class=\"tg-0lax\">Dog fish</td>\n    <td class=\"tg-baqh\">(vi)</td>\n    <td class=\"tg-0lax\">Placoid scales</td>\n  </tr>\n</tbody></table></p>",
          "options": [],
          "correct_options": [],
          "answer": null,
          "explanation": "<p>A. $\\rightarrow(\\mathrm{v})$\nB. $\\rightarrow$ (ii)\nC. $\\rightarrow$ (iii)\nD. $\\rightarrow$ (iv)\nE. $\\rightarrow$ (ii)\nF. $\\rightarrow$ (vi)</p>\n<p>A. Pila-Presence of shell Shell in Pila is an elongated structure which consists of a tubular whorl coiled around a central axis called columella. The main function of shell is to provide protection from harsh conditions.</p>\n<p>B. Cockroach-Jointed appendages Presence of jointed appendages along with segmented body is the characteristic feature of arthropods (e.g., spiders, bees, crabs etc).</p>\n<p>C. Asterias-Water vascular system It is the unique and characteristic feature in echinoderms. This system acts as a hydraulic system, composed of canals connecting numerous tube feet. It is very important as it helps Asterias (sea star) to move as well as to catch food. Respiration also takes place, through, water vascular system.</p>\n<p>D. Torpedo Electric organ. Torpedos are unique organisms, having two large kidney shaped electric organs. These organs are capable of generating high voltage electric shocks.</p>\n<p>E. Parrot-Perching Birds with the feet adapted (to hold tree branches are perching birds. The Passeriform birds are true perching birds with four toes, three directed forward and one backward.</p>\n<p>F. Dog fish-Placoid scales Placoid scales are tough scales that cover the skin of elasmobranchs (dog fish, sharks and rays). They are covered with hard enamel. The function of these scales is to protect against predators.</p>"
        }
      },
      "section": "exemplar-questions",
      "topic": null,
      "type": "subjective-short"
    },
    {
      "questionId": "bqf-mbosklzo",
      "book": "biology-xi",
      "bookGroup": "ncert",
      "chapter": "animal-kingdom",
      "chapterGroup": "zoology",
      "country": "in",
      "languages": [
        "en"
      ],
      "question": {
        "en": {
          "comprehension": null,
          "direction": null,
          "content": "<p>Differentiate between</p>\n<p>(a) Open and closed circulatory system</p>\n<p>(b) Oviparity and viviparity</p>\n<p>(c) Direct and indirect development</p>\n<p>(d) Acoelomate and pseudocoelomate</p>\n<p>(e) Notochord and nerve cord</p>\n<p>(f) Polyp and medusa</p>",
          "options": [],
          "correct_options": [],
          "answer": null,
          "explanation": "<p><style type=\"text/css\">\n.tg  {border-collapse:collapse;border-spacing:0;}\n.tg td{border-color:black;border-style:solid;border-width:1px;font-family:Arial, sans-serif;font-size:14px;\n  overflow:hidden;padding:10px 5px;word-break:normal;}\n.tg th{border-color:black;border-style:solid;border-width:1px;font-family:Arial, sans-serif;font-size:14px;\n  font-weight:normal;overflow:hidden;padding:10px 5px;word-break:normal;}\n.tg .tg-baqh{text-align:center;vertical-align:top}\n.tg .tg-amwm{font-weight:bold;text-align:center;vertical-align:top}\n.tg .tg-0lax{text-align:left;vertical-align:top}\n</style>\n<table class=\"tg\" style=\"undefined;table-layout: fixed; width: 604px\"><colgroup>\n<col style=\"width: 76px\">\n<col style=\"width: 260px\">\n<col style=\"width: 268px\">\n</colgroup>\n<thead>\n  <tr>\n    <th class=\"tg-amwm\">(d)</th>\n    <th class=\"tg-amwm\">Acoelomate</th>\n    <th class=\"tg-amwm\">Pseudocoelomate</th>\n  </tr></thead>\n<tbody>\n  <tr>\n    <td class=\"tg-amwm\"></td>\n    <td class=\"tg-0lax\">The animals without coelom are called as acoelomates<br>e.g., sponges, cnidarians, ctenophores and flatworms.<br><img src=\"https://app-content.cdn.examgoal.net/fly/@width/image/jaoe38c1mbt3typx/df6777fb-678e-4c82-8c09-4dbf3b7c23c6/8045c350-4765-11f0-9e4e-ff535330d4b4/file-jaoe38c1mbt3typy.webp?format=webp\" data-orsrc=\"https://app-content.cdn.examgoal.net/image/jaoe38c1mbt3typx/df6777fb-678e-4c82-8c09-4dbf3b7c23c6/8045c350-4765-11f0-9e4e-ff535330d4b4/file-jaoe38c1mbt3typy.webp\" loading=\"lazy\" style=\"max-width: 100%;height: auto;display: block;margin: 0 auto;max-height: 40vh;vertical-align: baseline\"></td>\n    <td class=\"tg-0lax\">The animals in which body cavity is derived from the blastocoel of the embryo are called pseudocoelomates. e.g., roundworms.<br><img src=\"https://app-content.cdn.examgoal.net/fly/@width/image/jaoe38c1mbt3vkfl/039d2827-6358-4fba-8769-42fad671e872/acdaba10-4765-11f0-9e4e-ff535330d4b4/file-jaoe38c1mbt3vkfm.webp?format=webp\" data-orsrc=\"https://app-content.cdn.examgoal.net/image/jaoe38c1mbt3vkfl/039d2827-6358-4fba-8769-42fad671e872/acdaba10-4765-11f0-9e4e-ff535330d4b4/file-jaoe38c1mbt3vkfm.webp\" loading=\"lazy\" style=\"max-width: 100%;height: auto;display: block;margin: 0 auto;max-height: 40vh;vertical-align: baseline\"></td>\n  </tr>\n  <tr>\n    <td class=\"tg-amwm\">(e)</td>\n    <td class=\"tg-amwm\">Notochord</td>\n    <td class=\"tg-amwm\">Nerve Cord</td>\n  </tr>\n  <tr>\n    <td class=\"tg-amwm\"></td>\n    <td class=\"tg-0lax\">Notochord is the skeletal rod which lies lengthwise between the central nervous system and the alimentary canal or the gut.<br>Vertebrates possess it at the young stage of development.<br>It is a part of skeleton system<br>In adults vertebrates, notocord is replaced by vertebral column.</td>\n    <td class=\"tg-0lax\">Nerve cord is the solid strand of nervous tissue forming a part of central nervous system, especially in invertebrates.</td>\n  </tr>\n  <tr>\n    <td class=\"tg-baqh\"><span style=\"font-weight:bold\">(f)</span></td>\n    <td class=\"tg-amwm\">Polyp</td>\n    <td class=\"tg-amwm\">Medusa</td>\n  </tr>\n  <tr>\n    <td class=\"tg-amwm\"></td>\n    <td class=\"tg-0lax\">Polyp is sessile and cylindrical form in Aurelia. Polyp produces medusa asexually<br><img src=\"https://app-content.cdn.examgoal.net/fly/@width/image/jaoe38c1mbt3wqxu/57dca489-248c-44ba-8c85-3f110f82a115/cdb0a420-4765-11f0-9e4e-ff535330d4b4/file-jaoe38c1mbt3wqxv.webp?format=webp\" data-orsrc=\"https://app-content.cdn.examgoal.net/image/jaoe38c1mbt3wqxu/57dca489-248c-44ba-8c85-3f110f82a115/cdb0a420-4765-11f0-9e4e-ff535330d4b4/file-jaoe38c1mbt3wqxv.webp\" loading=\"lazy\" style=\"max-width: 100%;height: auto;display: block;margin: 0 auto;max-height: 40vh;vertical-align: baseline\"></td>\n    <td class=\"tg-0lax\">Medusa is umbrella shaped and free swimming form in Aurelia.<br>Medusa forms polyp sexually.<br><img src=\"https://app-content.cdn.examgoal.net/fly/@width/image/jaoe38c1mbt3yg4s/cb40dc10-c883-4a52-a7f9-8376223d6ca1/fcf5c6c0-4765-11f0-9e4e-ff535330d4b4/file-jaoe38c1mbt3yg4t.webp?format=webp\" data-orsrc=\"https://app-content.cdn.examgoal.net/image/jaoe38c1mbt3yg4s/cb40dc10-c883-4a52-a7f9-8376223d6ca1/fcf5c6c0-4765-11f0-9e4e-ff535330d4b4/file-jaoe38c1mbt3yg4t.webp\" loading=\"lazy\" style=\"max-width: 100%;height: auto;display: block;margin: 0 auto;max-height: 40vh;vertical-align: baseline\"></td>\n  </tr>\n</tbody></table></p>"
        }
      },
      "section": "exemplar-questions",
      "topic": null,
      "type": "subjective-short"
    },
    {
      "questionId": "bqf-mboskjti",
      "book": "biology-xi",
      "bookGroup": "ncert",
      "chapter": "animal-kingdom",
      "chapterGroup": "zoology",
      "country": "in",
      "languages": [
        "en"
      ],
      "question": {
        "en": {
          "comprehension": null,
          "direction": null,
          "content": "<p>Give the characteristic features of the following citing one example of each</p>\n<p>(a) Chondrichthyes and ostichthyes</p>\n<p>(b) Urochordata and cephalochordata</p>",
          "options": [],
          "correct_options": [],
          "answer": null,
          "explanation": "<p>Characteristic features of different classes mentioned are as follows</p>\n<p>(a) Chondrichthyes</p>\n<p>(i) These are marine animals with a stream lined body.</p>\n<p>(ii) Body is has cartilaginous exoskeleton and the skin is tough due to the presence of minute placoid scales.</p>\n<p>(iii) These animals are predaceous.</p>\n<p>(iv) Due to the absence of air bladder they have to swim constantly to avoid sinking.</p>\n<p>(v) They are cold blooded animals e.g., Scoliodon (dog fish), Pristis (saw fish).</p>\n<p>(vi) Some of them possess electric organs and poison sting (Torpedo and Trygon).</p>\n<p>Osteichthyes</p>\n<p>(i) These animals are found in both habitats, i.e., marine and freshwater. They bear bony endoskeleton.</p>\n<p>(ii) Body is streamlined, posseses four pairs of gills covered by an operculum, on each side.</p>\n<p>(iii) Skin is covered by cycloid or ctenoid scales.</p>\n<p>(iv) Presence of air bladder is an additional feature providing buoyancy to animal.</p>\n<p>(v) Heart is two chambered.</p>\n<p>(vi) Sexes are seperate, fertilisation usually external, oviparous animal with direct development.</p>\n<p>e.g., marine- Exocoetus (flying fish), Hippocampus (sea horse); freshwaterLabeo (rohu).</p>\n<p>(b) Urochordata</p>\n<p>(i) In urochordates, notochord is only present in larval tail.</p>\n<p>(ii) They contain a tough outer covering called tunic.</p>\n<p>(iii) Persence of pharyngeal slits during some stage of the life cycle and a muscular, post anal tail is the characteristic features in urochordates.</p>\n<p>e.g., Salpa, Ascidia, Doliolum.</p>\n<p>Cephalochordata</p>\n<p>(i) Cephalochordates are exclusively marine animals.</p>\n<p>(ii) The notochord in cephalochordates extends, from the heart to tail region and is persistent throughout the life.</p>\n<p>(iii) Body-wall shows one cell thick, non-ciliated epidermis, connective tissue, striated muscle and parietal peritonium.</p>\n<p>(iv) Fertilisation is external</p>\n<p>e.g., Branchiostoma (Amphioxus or Lancelet).</p>"
        }
      },
      "section": "exemplar-questions",
      "topic": null,
      "type": "subjective-short"
    },
    {
      "questionId": "bqf-mboskiwg",
      "book": "biology-xi",
      "bookGroup": "ncert",
      "chapter": "animal-kingdom",
      "chapterGroup": "zoology",
      "country": "in",
      "languages": [
        "en"
      ],
      "question": {
        "en": {
          "comprehension": null,
          "direction": null,
          "content": "<p>Mention two similarities between</p>\n<p>(a) Aves and mammals</p>\n<p>(b) A frog and crocodile</p>\n<p>(c) A turtle and Pila</p>",
          "options": [],
          "correct_options": [],
          "answer": null,
          "explanation": "<p>(a) Similarities between aves and mammals</p>\n<p>(i) The members of both the groups are homeotherms, i.e., warm blooded. They are able to maintain constant body temperature.</p>\n<p>(ii) Heart is completely four chambered.</p>\n<p>(b) Similarities between frog and crocodile</p>\n<p>(i) The members of both the groups are poikilotherms, i.e., they lack the capacity to regulate their constant body temperature. They are cold blooded animals.</p>\n<p>(ii) Frog and crocodile are oviparous animals.</p>\n<p>(c) Similarities between turtle and Pila</p>\n<p>(i) In both animals, body is covered with dry and cornified skin. In turtle, the epidermal covering is known as scales whereas in case of Pila, it is known as calcareous shell.</p>\n<p>(ii) Both animals are oviparous.</p>"
        }
      },
      "section": "exemplar-questions",
      "topic": null,
      "type": "subjective-short"
    },
    {
      "questionId": "bqf-mboskjh4",
      "book": "biology-xi",
      "bookGroup": "ncert",
      "chapter": "animal-kingdom",
      "chapterGroup": "zoology",
      "country": "in",
      "languages": [
        "en"
      ],
      "question": {
        "en": {
          "comprehension": null,
          "direction": null,
          "content": "<p>Name</p>\n<p>(a) A limbless animal</p>\n<p>(b) A cold blooded animal</p>\n<p>(c) A warm blooded animal</p>\n<p>(d) An animal possessing dry and cornified skin</p>\n<p>(e) An animal having canal system and spicules</p>\n<p>(f) An animal with cnidoblasts</p>",
          "options": [],
          "correct_options": [],
          "answer": null,
          "explanation": "<p>(a) Ichthyophis does not possess limbs.</p>\n<p>(b) Scoliodon (dog fish) is a cold blooded animal.</p>\n<p>(c) Columba (pigeon) is a warm blooded animal.</p>\n<p>(d) Naja naja (snake) possesses dry and cornified skin.</p>\n<p>(e) Sycon (sponge) possesses canal system and bear spicules.</p>\n<p>(f) Obelia bears cnidoblast.</p>"
        }
      },
      "section": "exemplar-questions",
      "topic": null,
      "type": "subjective-short"
    },
    {
      "questionId": "bqf-mboskp3h",
      "book": "biology-xi",
      "bookGroup": "ncert",
      "chapter": "animal-kingdom",
      "chapterGroup": "zoology",
      "country": "in",
      "languages": [
        "en"
      ],
      "question": {
        "en": {
          "comprehension": null,
          "direction": null,
          "content": "<p>Give an example for each of the following</p>\n<p>(a) A viviparous animal</p>\n<p>(b) A fish possessing a poison sting</p>\n<p>(c) A fish possessing an electric organ</p>\n<p>(d) An organ, which regulates buoyancy</p>\n<p>(e) Animal, which exhibits alternation of generation</p>\n<p>(f) Oviparous animal with mammary gland</p>",
          "options": [],
          "correct_options": [],
          "answer": null,
          "explanation": "<p>(a) A viviparous animal is the one in which development of young ones is direct, later they provides nutrition to their offspring. It includes all mammals, except Platypus.</p>\n<p>(b) A fish possessing a poison sting is Trygon (sting-ray). It is found on its tail. The poison released is strong enough to stun an animal.</p>\n<p>(c) A fish possessing an electric organ Torpedo (electric ray). Electric organ in Torpedo is located in its big round pectoral fin which is just behind the eye. Large Torpedo can generate a fish killing current of up to 200 volts.</p>\n<p>(d) An organ, which regulates buoyancy is air bladder present in class-Osteichthyes. (e.g., Exocoetus, Catla).</p>\n<p>(e) Animal exhibiting alteration of generation is Aurelia or jelly fish of phylum-Cnidaria. It has two basic body forms called polyp and medusa are present. Polyp is sessile and cylindrical whereas medusa is umbrella shaped and free swimming form. Polyp produces medusa asexually and medusa forms polyps sexually (e.g., Obelia).</p>\n<p>(f) Oviparous animal with mammary gland is Ornithorhynchus (duck-billed platypes). Duck bill platypus is the only mammal which lays egg and also bear mammary gland, which is a characteristic feature of mammals.</p>"
        }
      },
      "section": "exemplar-questions",
      "topic": null,
      "type": "subjective-short"
    },
    {
      "questionId": "bqf-mbosknh3",
      "book": "biology-xi",
      "bookGroup": "ncert",
      "chapter": "animal-kingdom",
      "chapterGroup": "zoology",
      "country": "in",
      "languages": [
        "en"
      ],
      "question": {
        "en": {
          "comprehension": null,
          "direction": null,
          "content": "<p>Excretory organs of different animals are given below. Choose correctly and write in the space provided.</p>\n<p><style type=\"text/css\">\n.tg  {border-collapse:collapse;border-spacing:0;}\n.tg td{border-color:black;border-style:solid;border-width:1px;font-family:Arial, sans-serif;font-size:14px;\n  overflow:hidden;padding:10px 5px;word-break:normal;}\n.tg th{border-color:black;border-style:solid;border-width:1px;font-family:Arial, sans-serif;font-size:14px;\n  font-weight:normal;overflow:hidden;padding:10px 5px;word-break:normal;}\n.tg .tg-baqh{text-align:center;vertical-align:top}\n.tg .tg-amwm{font-weight:bold;text-align:center;vertical-align:top}\n.tg .tg-0lax{text-align:left;vertical-align:top}\n</style>\n<table class=\"tg\" style=\"undefined;table-layout: fixed; width: 565px\"><colgroup>\n<col style=\"width: 79px\">\n<col style=\"width: 182px\">\n<col style=\"width: 78px\">\n<col style=\"width: 226px\">\n</colgroup>\n<thead>\n  <tr>\n    <th class=\"tg-amwm\"></th>\n    <th class=\"tg-amwm\">Animal</th>\n    <th class=\"tg-amwm\"></th>\n    <th class=\"tg-amwm\">Excretory Organ/Unit</th>\n  </tr></thead>\n<tbody>\n  <tr>\n    <td class=\"tg-baqh\">A.</td>\n    <td class=\"tg-0lax\">Balanoglossus</td>\n    <td class=\"tg-baqh\">(i)</td>\n    <td class=\"tg-0lax\">Metanephridia</td>\n  </tr>\n  <tr>\n    <td class=\"tg-baqh\">B.</td>\n    <td class=\"tg-0lax\">Leech</td>\n    <td class=\"tg-baqh\">(ii)</td>\n    <td class=\"tg-0lax\">Nephridia</td>\n  </tr>\n  <tr>\n    <td class=\"tg-baqh\">C.</td>\n    <td class=\"tg-0lax\">Locust</td>\n    <td class=\"tg-baqh\">(iii)</td>\n    <td class=\"tg-0lax\">Flame cells</td>\n  </tr>\n  <tr>\n    <td class=\"tg-baqh\">D.</td>\n    <td class=\"tg-0lax\">Liver fluke</td>\n    <td class=\"tg-baqh\">(iv)</td>\n    <td class=\"tg-0lax\">Absent</td>\n  </tr>\n  <tr>\n    <td class=\"tg-baqh\">E.</td>\n    <td class=\"tg-0lax\">Sea urchin</td>\n    <td class=\"tg-baqh\">(v)</td>\n    <td class=\"tg-0lax\">Malpighian tubule</td>\n  </tr>\n  <tr>\n    <td class=\"tg-baqh\">F.</td>\n    <td class=\"tg-0lax\">Pila</td>\n    <td class=\"tg-baqh\">(vi)</td>\n    <td class=\"tg-0lax\">Proboscis gland</td>\n  </tr>\n</tbody></table></p>",
          "options": [],
          "correct_options": [],
          "answer": null,
          "explanation": "<p>A. $\\rightarrow$ (vi)\nB. $\\rightarrow$ (ii)\nC. $\\rightarrow$ (v)\nD. $\\rightarrow$ (iii)\nE. $\\rightarrow$ (vi)\nF. $\\rightarrow$ (i)</p>\n<p>A. Balanoglossus - Proboscis glands This gland present in front of central sinus and excretes brown granules.</p>\n<p>B. Leech Nephridia It helps in osmoregulation and excretion.</p>\n<p>C. Locust Malpighian tubules These tubules open into gut and help in excretion.</p>\n<p>D. Liver fluke Flame cells They are specialised cells in Platyhelminthes which helps in osmoregulation and excretion. These are also called protonephridia.</p>\n<p>E. Sea urchin-absent Specialised excretory organs are absent in sea urchin.</p>\n<p>F. Pila-Metanephridia It is a type of excretory gland or nephridium found in many types of invertebrates such as annelids, arthropods, and molluscs (in molluscs nephridia is also known as Bojanus organ).</p>"
        }
      },
      "section": "exemplar-questions",
      "topic": null,
      "type": "subjective-short"
    },
    {
      "questionId": "bqf-mbosklfj",
      "book": "biology-xi",
      "bookGroup": "ncert",
      "chapter": "animal-kingdom",
      "chapterGroup": "zoology",
      "country": "in",
      "languages": [
        "en"
      ],
      "question": {
        "en": {
          "comprehension": null,
          "direction": null,
          "content": "<p>Give three major differences between chordates and non chordates and draw a schematic sketch of a chordate showing those features.</p>",
          "options": [],
          "correct_options": [],
          "answer": null,
          "explanation": "<p>The major differences between Chordates and Non-chordates are as follows</p>\n<p><style type=\"text/css\">\n.tg  {border-collapse:collapse;border-spacing:0;}\n.tg td{border-color:black;border-style:solid;border-width:1px;font-family:Arial, sans-serif;font-size:14px;\n  overflow:hidden;padding:10px 5px;word-break:normal;}\n.tg th{border-color:black;border-style:solid;border-width:1px;font-family:Arial, sans-serif;font-size:14px;\n  font-weight:normal;overflow:hidden;padding:10px 5px;word-break:normal;}\n.tg .tg-c3ow{border-color:inherit;text-align:center;vertical-align:top}\n.tg .tg-7btt{border-color:inherit;font-weight:bold;text-align:center;vertical-align:top}\n.tg .tg-0pky{border-color:inherit;text-align:left;vertical-align:top}\n</style>\n<table class=\"tg\" style=\"undefined;table-layout: fixed; width: 487px\"><colgroup>\n<col style=\"width: 79px\">\n<col style=\"width: 182px\">\n<col style=\"width: 226px\">\n</colgroup>\n<thead>\n  <tr>\n    <th class=\"tg-7btt\"></th>\n    <th class=\"tg-7btt\">Chordates</th>\n    <th class=\"tg-7btt\">Non-Chordates</th>\n  </tr></thead>\n<tbody>\n  <tr>\n    <td class=\"tg-c3ow\">1.</td>\n    <td class=\"tg-0pky\">A notochord is present at some stage in the life cycle of a chordate.</td>\n    <td class=\"tg-0pky\">Notochord is not present at any stage in the life cycle of a non-chordate.</td>\n  </tr>\n  <tr>\n    <td class=\"tg-c3ow\">2.</td>\n    <td class=\"tg-0pky\">Gill-slits are present in the pharynx either in embryo or in adult organism.</td>\n    <td class=\"tg-0pky\">Pharyngeal gill slits are absent.</td>\n  </tr>\n  <tr>\n    <td class=\"tg-c3ow\">3.</td>\n    <td class=\"tg-0pky\">Tail is present at some stage in the life of the chordate.</td>\n    <td class=\"tg-0pky\">Tail is absent in non-chordates.</td>\n  </tr>\n  <tr>\n    <td class=\"tg-c3ow\">4.</td>\n    <td class=\"tg-0pky\">Heart is ventrally located.</td>\n    <td class=\"tg-0pky\">Heart (if present) is dorsally located.</td>\n  </tr>\n  <tr>\n    <td class=\"tg-c3ow\">5.</td>\n    <td class=\"tg-0pky\">Central nervous system is dorsal and hollow in chordates.</td>\n    <td class=\"tg-0pky\">Central nervous system in non-chordates is solid and ventrally located.</td>\n  </tr>\n</tbody></table></p>\n<p>Schematic sketch illustrating important characters of chordates is shown below</p>\n<p><img src=\"https://app-content.cdn.examgoal.net/fly/@width/image/jaoe38c1mbt41ky3/59d9ecd3-2650-4c17-82ae-0c0d29b3bec9/541b31b0-4766-11f0-9e4e-ff535330d4b4/file-jaoe38c1mbt41ky4.webp?format=webp\" data-orsrc=\"https://app-content.cdn.examgoal.net/image/jaoe38c1mbt41ky3/59d9ecd3-2650-4c17-82ae-0c0d29b3bec9/541b31b0-4766-11f0-9e4e-ff535330d4b4/file-jaoe38c1mbt41ky4.webp\" loading=\"lazy\" style=\"max-width: 100%;height: auto;display: block;margin: 0 auto;max-height: 40vh;vertical-align: baseline\"></p>"
        }
      },
      "section": "exemplar-questions",
      "topic": null,
      "type": "subjective-long"
    },
    {
      "questionId": "bqf-mboskl43",
      "book": "biology-xi",
      "bookGroup": "ncert",
      "chapter": "animal-kingdom",
      "chapterGroup": "zoology",
      "country": "in",
      "languages": [
        "en"
      ],
      "question": {
        "en": {
          "comprehension": null,
          "direction": null,
          "content": "<p>What is the relationship between germinal layers and the formation of body cavity in case of coelomate, acoelomates and pseudocoelomates?</p>",
          "options": [],
          "correct_options": [],
          "answer": null,
          "explanation": "<p>All adult multicellular organisms typically possess a concentric arrangement of tissues in the body. These tissues are derived from the three embryonic cell layers called germinal layers.</p>\n<p>(i) The outer layer is the ectoderm, the middle layer is the mesoderm and the innermost layer is the endoderm.</p>\n<p>(ii) Endoderm layer is associated with the formation of the stomach, colon, liver, pancreas, urinary bladder and other vital organs in an organism.</p>\n<p>(iii) Mesoderm forms the main structural components of the body like the skeletal muscles, the skeleton, the dermis of the skin connective tissue, etc.</p>\n<p>(iv) Ectoderm is associated with the formation of CNS, eye lens, ganglia, nerves and glands.</p>\n<p>(v) The body cavity that is lined by mesoderm is called coelom, and the animals possessing coelom are called as coelomates. e.g., phylum-Annelida, Mollusca, Arthropoda, Echinodermata, Hemichordata and Chordata.</p>\n<p>(vi) In some organisms, body cavity is not lined by mesoderm, instead mesoderm is present in the form of scattered pouches in between ectoderm and endoderm, Such body cavity is called pseudocoelom and animals possessing there stusturs are refered to as pseudocoelomates e.g., Ascaris.</p>\n<p>(vii) The animals in which there is complete absence of body cavity are called acoelomates. e.g., Platyhelminthes.</p>\n<p><img src=\"https://app-content.cdn.examgoal.net/fly/@width/image/jaoe38c1mbt44cs6/8b0385f9-b240-4377-8d1a-4ec0ca63f3d8/a13a1560-4766-11f0-9e4e-ff535330d4b4/file-jaoe38c1mbt44cs7.webp?format=webp\" data-orsrc=\"https://app-content.cdn.examgoal.net/image/jaoe38c1mbt44cs6/8b0385f9-b240-4377-8d1a-4ec0ca63f3d8/a13a1560-4766-11f0-9e4e-ff535330d4b4/file-jaoe38c1mbt44cs7.webp\" loading=\"lazy\" style=\"max-width: 100%;height: auto;display: block;margin: 0 auto;max-height: 40vh;vertical-align: baseline\"></p>"
        }
      },
      "section": "exemplar-questions",
      "topic": null,
      "type": "subjective-long"
    },
    {
      "questionId": "bqf-mboskmks",
      "book": "biology-xi",
      "bookGroup": "ncert",
      "chapter": "animal-kingdom",
      "chapterGroup": "zoology",
      "country": "in",
      "languages": [
        "en"
      ],
      "question": {
        "en": {
          "comprehension": null,
          "direction": null,
          "content": "<p>Comment upon the habitats and external features of animals belonging to class-Amphibia and Reptilia.</p>",
          "options": [],
          "correct_options": [],
          "answer": null,
          "explanation": "<p>Amphibians</p>\n<p>(i) They possess dual life as they can live in aquatic as well as terrestrial habitat. They are ectothermic (cold blooded).</p>\n<p>(ii) They are tetrapods (4 limbs) which facilitate movement land.</p>\n<p>(iiii) Their limbs are evolved from the pectoral and pelvic fins.</p>\n<p>(iv) Skin is thin, covered by mucus and mostly remain moist, also serves as an accessory source oxygen.</p>\n<p>(v) They are both gill and lung breathers; usually gills appear in th larval stage, replaced by lungs in the adults stage.</p>\n<p>(vi) They possess three chambered heart with two atria and one ventricle.</p>\n<p>(vii) The fertilisation is mostly external, females are oviparous.</p>\n<p>(viii) Larva is a tadpole, which metamorphosis into adult thus shaving metamorphosis. e.g., Rana frog, Nectureus (mud puppy), Salamandera (salamander).</p>\n<p><img src=\"https://app-content.cdn.examgoal.net/fly/@width/image/jaoe38c1mbt47xys/c18fdb16-ee99-4299-95be-36ec9b15272f/0504a740-4767-11f0-9e4e-ff535330d4b4/file-jaoe38c1mbt47xyt.webp?format=webp\" data-orsrc=\"https://app-content.cdn.examgoal.net/image/jaoe38c1mbt47xys/c18fdb16-ee99-4299-95be-36ec9b15272f/0504a740-4767-11f0-9e4e-ff535330d4b4/file-jaoe38c1mbt47xyt.webp\" loading=\"lazy\" style=\"max-width: 100%;height: auto;display: block;margin: 0 auto;max-height: 40vh;vertical-align: baseline\"></p>\n<p>Reptiles</p>\n<p>(i) In reptiles, creeping and crawling mode of locomotion is found.</p>\n<p>(ii) They are mostly terrestrial animals and their body is covered by dry, and cornified skin, epidermal scales or scutes.</p>\n<p>(iii) Lungs are well developed and present in all stages of life.</p>\n<p>(iv) Toes possess claws.</p>\n<p>(v) Appendages are well adapted for the movement on land.</p>\n<p>(vi) Heart possesses a partially divided ventricle and 2 atria.</p>\n<p>(vii) They lay amniotic eggs which are incubate on land.</p>\n<p>(viii) They are poikilothermic or cold blooded animals. Temperature is regulated mechanically and not metabolically by moving in and out; heat source is usually the sun.</p>\n<p>(ix) fertilisation is internal They are oviparous and development of young ones is direc.</p>\n<p>e.g., Chelone (turtle), Naja (cobra), Crocodicus (crocodile).</p>\n<p><img src=\"https://app-content.cdn.examgoal.net/fly/@width/image/jaoe38c1mbt49eq7/14b089f0-a4f0-4b6c-bc87-4a850bcf47e7/2dc69d00-4767-11f0-9e4e-ff535330d4b4/file-jaoe38c1mbt49eq8.webp?format=webp\" data-orsrc=\"https://app-content.cdn.examgoal.net/image/jaoe38c1mbt49eq7/14b089f0-a4f0-4b6c-bc87-4a850bcf47e7/2dc69d00-4767-11f0-9e4e-ff535330d4b4/file-jaoe38c1mbt49eq8.webp\" loading=\"lazy\" style=\"max-width: 100%;height: auto;display: block;margin: 0 auto;max-height: 40vh;vertical-align: baseline\"></p>"
        }
      },
      "section": "exemplar-questions",
      "topic": null,
      "type": "subjective-long"
    },
    {
      "questionId": "bqf-mboskpop",
      "book": "biology-xi",
      "bookGroup": "ncert",
      "chapter": "animal-kingdom",
      "chapterGroup": "zoology",
      "country": "in",
      "languages": [
        "en"
      ],
      "question": {
        "en": {
          "comprehension": null,
          "direction": null,
          "content": "<p>Mammals are most adapted among the vertebrates elaborate.</p>",
          "options": [],
          "correct_options": [],
          "answer": null,
          "explanation": "<p> Mammals are most adapted among the vertebrates and the following features explain the justify this statement.</p>\n<p>(i) They are found in variety of habitats, i.e., polar ice caps,deserts, mountains, forests, grasslands and dark caves.</p>\n<p>(ii) They have better developed brain. The brain bears large cerebellum and cerebrum.</p>\n<p>(iii) The most unique mammalian characteristic is the presence of milk producing glands (mammary glands) by which mammals nourish their young ones.</p>\n<p>(iv) Mammals are homeotherms (warm blooded), i.e., they are capable of maintaining their body temperature regardless of to the surrounding environment.</p>\n<p>(v) They possess oil secreting glands (sebaceous glands) and sweat glands (sudoriferous glands) in the skin.</p>\n<p>(vi) They possess two pair of limbs, that are well adapted for walking, running, climbing, burrowing, swimming and flying.</p>\n<p>(vii) fertilisation is internal. They show viviparity with few exceptions e.g., oviparous Ornithorhynchus (platypus) and the development is direct. e.g., viviparous - Macropus (kangaroo), Rattus (rat), Canis (dog), Delphinus (common dolphin), Panthera tigris (tiger), etc.</p>"
        }
      },
      "section": "exemplar-questions",
      "topic": null,
      "type": "subjective-long"
    }
  ]
}